Workbook
Name Slicer_Sales_Channel: #N/A
Name Slicer_Order_Status: #N/A
Name Slicer_Customer_Segment: #N/A

Sheet Customers_Raw
A1: Customer_ID | B1: Customer_Name | C1: City | D1: Signup_Date | E1: Customer_Segment
A2: C10001 | B2: Rahul Kumar | C2: Hyderabad | D2: 45815 | E2: Small Business
A3: C10002 | B3: Kavya Arora | C3: Amritsar | D3: 45692 | E3: Corporate
A4: C10003 | B4: Vikram Khanna | C4: Amritsar | D4: 45996 | E4: Corporate
A5: C10004 | B5: Rahul Chawla | C5: Delhi | D5: 45313 | E5: Consumer
A6: C10005 | B6: Pooja Mehta | C6: Jaipur | D6: 45765 | E6: Consumer
A7: C10006 | B7: Diya Arora | C7: Chandigarh | D7: 45411 | E7: Consumer
A8: C10007 | B8: Arjun Kapoor | C8: Jaipur | D8: 45501 | E8: Corporate
A9: C10008 | B9: Aditya Malhotra | C9: Mumbai | D9: 45597 | E9: Consumer
A10: C10009 | B10: Vivaan Kapoor | C10: Chandigarh | D10: 45561 | E10: Consumer
A11: C10010 | B11: Isha Joshi | C11: Hyderabad | D11: 45995 | E11: Small Business
A12: C10011 | B12: Karan Verma | C12: Mumbai | D12: 45978 | E12: Consumer
A13: C10012 | B13: Aarav Sethi | C13: Pune | D13: 45576 | E13: Consumer
... A24: C10023 | B24: Neha Kumar | C24: Mumbai | D24: 45750 | E24: Small Business
A25: C10024 | C25: Amritsar | D25: 45861 | E25: Corporate
A26: C10025 | B26: Nikhil Chawla | C26: Gurugram | D26: 45829 | E26: Consumer
A27: C10026 | B27: Vivaan Kumar | C27: Noida | D27: 45773 | E27: Consumer
A28: C10027 | B28: Kavya Sethi | C28: Pune | D28: 45721 | E28: Consumer
A29: C10028 | B29: Rahul Sethi | C29: Chandigarh | D29: 45576 | E29: Consumer
A30: C10029 | B30: Vikram Mishra | C30: Gurugram | D30: 45807 | E30: Consumer
A31: C10030 | B31: Aditya Joshi | C31: Noida | D31: 45390 | E31: Consumer
A32: C10031 | B32: Riya Kumar | C32: Ludhiana | D32: 45688 | E32: Consumer
A33: C10032 | B33: Neha Kapoor | C33: Jaipur | D33: 45780 | E33: Consumer
A34: C10033 | B34: Arjun Verma | C34: Delhi | D34: 45330 | E34: Consumer
A35: C10034 | B35: Karan Malhotra | C35: Pune | D35: 45562 | E35: Consumer
A36: C10035 | B36: Ananya Kumar | C36: Delhi | D36: 45448 | E36: Corporate
A37: C10036 | B37: Neha Chawla | C37: Pune | D37: 45366 | E37: Consumer
... A601: C10600 | B601: Diya Sethi | C601: Chandigarh | D601: 45839 | E601: Consumer

Sheet Orders_Raw
A1: Order_ID | B1: Customer_ID | C1: Order_Date | D1: Order_Status | E1: Sales_Channel | F1: Payment_Method | G1: Customer_Segment
A2: O50001 | B2: C10139 | C2: 45692 | D2: Shipped | E2: Website | F2: Net Banking | G2: =_xlfn.XLOOKUP(Orders_Raw!B2,Customers_Raw!A:A,Customers_Raw!E:E) -> Consumer
A3: O50002 | B3: C10359 | C3: 45840 | D3: Shipped | E3: Website | F3: Credit Card | G3: =_xlfn.XLOOKUP(Orders_Raw!B3,Customers_Raw!A:A,Customers_Raw!E:E) -> Consumer
A4: O50003 | B4: C10499 | C4: 45927 | D4: Shipped | E4: Website | F4: UPI | G4: =_xlfn.XLOOKUP(Orders_Raw!B4,Customers_Raw!A:A,Customers_Raw!E:E) -> Consumer
A5: O50004 | B5: C10385 | C5: 46015 | D5: Delivered | E5: Mobile App | F5: Credit Card | G5: =_xlfn.XLOOKUP(Orders_Raw!B5,Customers_Raw!A:A,Customers_Raw!E:E) -> Consumer
A6: O50005 | B6: C10280 | C6: 45757 | D6: Delivered | E6: Marketplace | F6: Net Banking | G6: =_xlfn.XLOOKUP(Orders_Raw!B6,Customers_Raw!A:A,Customers_Raw!E:E) -> Corporate
A7: O50006 | B7: C10483 | C7: 45664 | D7: Delivered | E7: Mobile App | F7: Debit Card | G7: =_xlfn.XLOOKUP(Orders_Raw!B7,Customers_Raw!A:A,Customers_Raw!E:E) -> Corporate
A8: O50007 | B8: C10111 | C8: 45687 | D8: Cancelled | E8: Website | F8: Debit Card | G8: =_xlfn.XLOOKUP(Orders_Raw!B8,Customers_Raw!A:A,Customers_Raw!E:E) -> Corporate
A9: O50008 | B9: C10139 | C9: 45962 | D9: Delivered | E9: Mobile App | F9: UPI | G9: =_xlfn.XLOOKUP(Orders_Raw!B9,Customers_Raw!A:A,Customers_Raw!E:E) -> Consumer
A10: O50009 | B10: C10435 | C10: 45801 | D10: Delivered | E10: Mobile App | F10: COD | G10: =_xlfn.XLOOKUP(Orders_Raw!B10,Customers_Raw!A:A,Customers_Raw!E:E) -> Consumer
A11: O50010 | B11: C10509 | C11: 45768 | D11: Delivered | E11: Website | F11: Credit Card | G11: =_xlfn.XLOOKUP(Orders_Raw!B11,Customers_Raw!A:A,Customers_Raw!E:E) -> Corporate
A12: O50011 | B12: C10273 | C12: 45889 | D12: Delivered | E12: Marketplace | F12: Debit Card | G12: =_xlfn.XLOOKUP(Orders_Raw!B12,Customers_Raw!A:A,Customers_Raw!E:E) -> Corporate
A13: O50012 | B13: C10099 | C13: 45836 | D13: Delivered | E13: Website | F13: UPI | G13: =_xlfn.XLOOKUP(Orders_Raw!B13,Customers_Raw!A:A,Customers_Raw!E:E) -> Corporate
... A2501: O52500 | B2501: C10492 | C2501: 45892 | D2501: Delivered | E2501: Mobile App | F2501: Credit Card | G2501: =_xlfn.XLOOKUP(Orders_Raw!B2501,Customers_Raw!A:A,Customers_Raw!E:E) -> Corporate

Sheet Order_Items_Raw
A1: Order_ID | B1: Product_ID | C1: Quantity | D1: Line_Revenue | E1: Unit_Cost | F1: Gross_Profit | G1: Sales_Channel | H1: Category | I1: Customer_Segment | J1: Order_Date | K1: Order_Month | L1: Order Status | M1: Customer Segment | N1: Order_Flag
A2: O51025 | B2: P1001 | C2: 3 | D2: 18176.21 | E2: =_xlfn.XLOOKUP(Order_Items_Raw!B21,Products_Raw!A:A,Products_Raw!D:D) -> 10361.65 | F2: =D2-(C2*E2) -> -12908.74 | G2: =PROPER(TRIM(CLEAN(_xlfn.XLOOKUP(Order_Items_Raw!A21,Orders_Raw!A:A,Orders_Raw!E:E)))) -> Website | H2: =_xlfn.XLOOKUP(B2,Products_Raw!A:A,Products_Raw!C:C) -> Sports | I2: =_xlfn.XLOOKUP(_xlfn.XLOOKUP(A2,Orders_Raw!A:A,Orders_Raw!B:B),Customers_Raw!A:A,Customers_Raw!E:E) -> Consumer | J2: =_xlfn.XLOOKUP(Order_Items_Raw!A21,Orders_Raw!A:A,Orders_Raw!C:C) -> 45762 | K2: Apr | L2: =_xlfn.XLOOKUP(A2,Orders_Raw!A:A,Orders_Raw!D:D) -> Delivered | M2: =_xlfn.XLOOKUP(_xlfn.XLOOKUP(A2,Orders_Raw!A:A,Orders_Raw!B:B),Customers_Raw!A:A,Customers_Raw!E:E) -> Consumer | N2: =IF(COUNTIF($A$2:A2,A2)=1,1,0) -> 1
A3: O52146 | B3: P1001 | C3: 1 | D3: 7201.05 | E3: =_xlfn.XLOOKUP(Order_Items_Raw!B38,Products_Raw!A:A,Products_Raw!D:D) -> 9148.31 | F3: =D3-(C3*E3) -> -1947.26 | G3: =PROPER(TRIM(CLEAN(_xlfn.XLOOKUP(Order_Items_Raw!A38,Orders_Raw!A:A,Orders_Raw!E:E)))) -> Website | H3: =_xlfn.XLOOKUP(B3,Products_Raw!A:A,Products_Raw!C:C) -> Sports | I3: =_xlfn.XLOOKUP(_xlfn.XLOOKUP(A3,Orders_Raw!A:A,Orders_Raw!B:B),Customers_Raw!A:A,Customers_Raw!E:E) -> Consumer | J3: =_xlfn.XLOOKUP(Order_Items_Raw!A38,Orders_Raw!A:A,Orders_Raw!C:C) -> 45771 | K3: Apr | L3: =_xlfn.XLOOKUP(A3,Orders_Raw!A:A,Orders_Raw!D:D) -> Processing | M3: =_xlfn.XLOOKUP(_xlfn.XLOOKUP(A3,Orders_Raw!A:A,Orders_Raw!B:B),Customers_Raw!A:A,Customers_Raw!E:E) -> Consumer | N3: =IF(COUNTIF($A$2:A3,A3)=1,1,0) -> 1
A4: O51186 | B4: P1002 | C4: 4 | D4: 54525.46 | E4: =_xlfn.XLOOKUP(Order_Items_Raw!B65,Products_Raw!A:A,Products_Raw!D:D) -> 4806.74 | F4: =D4-(C4*E4) -> 35298.5 | G4: =PROPER(TRIM(CLEAN(_xlfn.XLOOKUP(Order_Items_Raw!A65,Orders_Raw!A:A,Orders_Raw!E:E)))) -> Mobile App | H4: =_xlfn.XLOOKUP(B4,Products_Raw!A:A,Products_Raw!C:C) -> Sports | I4: =_xlfn.XLOOKUP(_xlfn.XLOOKUP(A4,Orders_Raw!A:A,Orders_Raw!B:B),Customers_Raw!A:A,Customers_Raw!E:E) -> Small Business | J4: =_xlfn.XLOOKUP(Order_Items_Raw!A65,Orders_Raw!A:A,Orders_Raw!C:C) -> 45754 | K4: Apr | L4: =_xlfn.XLOOKUP(A4,Orders_Raw!A:A,Orders_Raw!D:D) -> Delivered | M4: =_xlfn.XLOOKUP(_xlfn.XLOOKUP(A4,Orders_Raw!A:A,Orders_Raw!B:B),Customers_Raw!A:A,Customers_Raw!E:E) -> Small Business | N4: =IF(COUNTIF($A$2:A4,A4)=1,1,0) -> 1
A5: O51398 | B5: P1002 | C5: 2 | D5: 24468.58 | E5: =_xlfn.XLOOKUP(Order_Items_Raw!B72,Products_Raw!A:A,Products_Raw!D:D) -> 6213.42 | F5: =D5-(C5*E5) -> 12041.74 | G5: =PROPER(TRIM(CLEAN(_xlfn.XLOOKUP(Order_Items_Raw!A72,Orders_Raw!A:A,Orders_Raw!E:E)))) -> Marketplace | H5: =_xlfn.XLOOKUP(B5,Products_Raw!A:A,Products_Raw!C:C) -> Sports | I5: =_xlfn.XLOOKUP(_xlfn.XLOOKUP(A5,Orders_Raw!A:A,Orders_Raw!B:B),Customers_Raw!A:A,Customers_Raw!E:E) -> Consumer | J5: =_xlfn.XLOOKUP(Order_Items_Raw!A72,Orders_Raw!A:A,Orders_Raw!C:C) -> 45757 | K5: Apr | L5: =_xlfn.XLOOKUP(A5,Orders_Raw!A:A,Orders_Raw!D:D) -> Delivered | M5: =_xlfn.XLOOKUP(_xlfn.XLOOKUP(A5,Orders_Raw!A:A,Orders_Raw!B:B),Customers_Raw!A:A,Customers_Raw!E:E) -> Consumer | N5: =IF(COUNTIF($A$2:A5,A5)=1,1,0) -> 1
A6: O52459 | B6: P1002 | C6: 2 | D6: 29750.74 | E6: =_xlfn.XLOOKUP(Order_Items_Raw!B89,Products_Raw!A:A,Products_Raw!D:D) -> 680.62 | F6: =D6-(C6*E6) -> 28389.5 | G6: =PROPER(TRIM(CLEAN(_xlfn.XLOOKUP(Order_Items_Raw!A89,Orders_Raw!A:A,Orders_Raw!E:E)))) -> Mobile App | H6: =_xlfn.XLOOKUP(B6,Products_Raw!A:A,Products_Raw!C:C) -> Sports | I6: =_xlfn.XLOOKUP(_xlfn.XLOOKUP(A6,Orders_Raw!A:A,Orders_Raw!B:B),Customers_Raw!A:A,Customers_Raw!E:E) -> Consumer | J6: =_xlfn.XLOOKUP(Order_Items_Raw!A89,Orders_Raw!A:A,Orders_Raw!C:C) -> 45751 | K6: Apr | L6: =_xlfn.XLOOKUP(A6,Orders_Raw!A:A,Orders_Raw!D:D) -> Delivered | M6: =_xlfn.XLOOKUP(_xlfn.XLOOKUP(A6,Orders_Raw!A:A,Orders_Raw!B:B),Customers_Raw!A:A,Customers_Raw!E:E) -> Consumer | N6: =IF(COUNTIF($A$2:A6,A6)=1,1,0) -> 1
A7: O50090 | B7: P1003 | C7: 3 | D7: 18086.3 | E7: =_xlfn.XLOOKUP(Order_Items_Raw!B90,Products_Raw!A:A,Products_Raw!D:D) -> 680.62 | F7: =D7-(C7*E7) -> 16044.44 | G7: =PROPER(TRIM(CLEAN(_xlfn.XLOOKUP(Order_Items_Raw!A90,Orders_Raw!A:A,Orders_Raw!E:E)))) -> Mobile App | H7: =_xlfn.XLOOKUP(B7,Products_Raw!A:A,Products_Raw!C:C) -> Sports | I7: =_xlfn.XLOOKUP(_xlfn.XLOOKUP(A7,Orders_Raw!A:A,Orders_Raw!B:B),Customers_Raw!A:A,Customers_Raw!E:E) -> Corporate | J7: =_xlfn.XLOOKUP(Order_Items_Raw!A90,Orders_Raw!A:A,Orders_Raw!C:C) -> 45765 | K7: Apr | L7: =_xlfn.XLOOKUP(A7,Orders_Raw!A:A,Orders_Raw!D:D) -> Delivered | M7: =_xlfn.XLOOKUP(_xlfn.XLOOKUP(A7,Orders_Raw!A:A,Orders_Raw!B:B),Customers_Raw!A:A,Customers_Raw!E:E) -> Corporate | N7: =IF(COUNTIF($A$2:A7,A7)=1,1,0) -> 1
A8: O50207 | B8: P1003 | C8: 1 | D8: 7413.85 | E8: =_xlfn.XLOOKUP(Order_Items_Raw!B92,Products_Raw!A:A,Products_Raw!D:D) -> 11367.74 | F8: =D8-(C8*E8) -> -3953.89 | G8: =PROPER(TRIM(CLEAN(_xlfn.XLOOKUP(Order_Items_Raw!A92,Orders_Raw!A:A,Orders_Raw!E:E)))) -> Mobile App | H8: =_xlfn.XLOOKUP(B8,Products_Raw!A:A,Products_Raw!C:C) -> Sports | I8: =_xlfn.XLOOKUP(_xlfn.XLOOKUP(A8,Orders_Raw!A:A,Orders_Raw!B:B),Customers_Raw!A:A,Customers_Raw!E:E) -> Consumer | J8: =_xlfn.XLOOKUP(Order_Items_Raw!A92,Orders_Raw!A:A,Orders_Raw!C:C) -> 45755 | K8: Apr | L8: =_xlfn.XLOOKUP(A8,Orders_Raw!A:A,Orders_Raw!D:D) -> Delivered | M8: =_xlfn.XLOOKUP(_xlfn.XLOOKUP(A8,Orders_Raw!A:A,Orders_Raw!B:B),Customers_Raw!A:A,Customers_Raw!E:E) -> Consumer | N8: =IF(COUNTIF($A$2:A8,A8)=1,1,0) -> 1
A9: O51279 | B9: P1003 | C9: 4 | D9: 31497.12 | E9: =_xlfn.XLOOKUP(Order_Items_Raw!B112,Products_Raw!A:A,Products_Raw!D:D) -> 229.52 | F9: =D9-(C9*E9) -> 30579.04 | G9: =PROPER(TRIM(CLEAN(_xlfn.XLOOKUP(Order_Items_Raw!A112,Orders_Raw!A:A,Orders_Raw!E:E)))) -> Marketplace | H9: =_xlfn.XLOOKUP(B9,Products_Raw!A:A,Products_Raw!C:C) -> Sports | I9: =_xlfn.XLOOKUP(_xlfn.XLOOKUP(A9,Orders_Raw!A:A,Orders_Raw!B:B),Customers_Raw!A:A,Customers_Raw!E:E) -> Consumer | J9: =_xlfn.XLOOKUP(Order_Items_Raw!A112,Orders_Raw!A:A,Orders_Raw!C:C) -> 45751 | K9: Apr | L9: =_xlfn.XLOOKUP(A9,Orders_Raw!A:A,Orders_Raw!D:D) -> Delivered | M9: =_xlfn.XLOOKUP(_xlfn.XLOOKUP(A9,Orders_Raw!A:A,Orders_Raw!B:B),Customers_Raw!A:A,Customers_Raw!E:E) -> Consumer | N9: =IF(COUNTIF($A$2:A9,A9)=1,1,0) -> 1
A10: O51549 | B10: P1003 | C10: 2 | D10: 11986.74 | E10: =_xlfn.XLOOKUP(Order_Items_Raw!B115,Products_Raw!A:A,Products_Raw!D:D) -> 9531.89 | F10: =D10-(C10*E10) -> -7077.04 | G10: =PROPER(TRIM(CLEAN(_xlfn.XLOOKUP(Order_Items_Raw!A115,Orders_Raw!A:A,Orders_Raw!E:E)))) -> Marketplace | H10: =_xlfn.XLOOKUP(B10,Products_Raw!A:A,Products_Raw!C:C) -> Sports | I10: =_xlfn.XLOOKUP(_xlfn.XLOOKUP(A10,Orders_Raw!A:A,Orders_Raw!B:B),Customers_Raw!A:A,Customers_Raw!E:E) -> Small Business | J10: =_xlfn.XLOOKUP(Order_Items_Raw!A115,Orders_Raw!A:A,Orders_Raw!C:C) -> 45754 | K10: Apr | L10: =_xlfn.XLOOKUP(A10,Orders_Raw!A:A,Orders_Raw!D:D) -> Delivered | M10: =_xlfn.XLOOKUP(_xlfn.XLOOKUP(A10,Orders_Raw!A:A,Orders_Raw!B:B),Customers_Raw!A:A,Customers_Raw!E:E) -> Small Business | N10: =IF(COUNTIF($A$2:A10,A10)=1,1,0) -> 1
A11: O51620 | B11: P1003 | C11: 4 | D11: 31246.92 | E11: =_xlfn.XLOOKUP(Order_Items_Raw!B121,Products_Raw!A:A,Products_Raw!D:D) -> 7212.47 | F11: =D11-(C11*E11) -> 2397.04 | G11: =PROPER(TRIM(CLEAN(_xlfn.XLOOKUP(Order_Items_Raw!A121,Orders_Raw!A:A,Orders_Raw!E:E)))) -> Mobile App | H11: =_xlfn.XLOOKUP(B11,Products_Raw!A:A,Products_Raw!C:C) -> Sports | I11: =_xlfn.XLOOKUP(_xlfn.XLOOKUP(A11,Orders_Raw!A:A,Orders_Raw!B:B),Customers_Raw!A:A,Customers_Raw!E:E) -> Consumer | J11: =_xlfn.XLOOKUP(Order_Items_Raw!A121,Orders_Raw!A:A,Orders_Raw!C:C) -> 45769 | K11: Apr | L11: =_xlfn.XLOOKUP(A11,Orders_Raw!A:A,Orders_Raw!D:D) -> Cancelled | M11: =_xlfn.XLOOKUP(_xlfn.XLOOKUP(A11,Orders_Raw!A:A,Orders_Raw!B:B),Customers_Raw!A:A,Customers_Raw!E:E) -> Consumer | N11: =IF(COUNTIF($A$2:A11,A11)=1,1,0) -> 1
A12: O51717 | B12: P1003 | C12: 3 | D12: 18926.73 | E12: =_xlfn.XLOOKUP(Order_Items_Raw!B125,Products_Raw!A:A,Products_Raw!D:D) -> 1349.93 | F12: =D12-(C12*E12) -> 14876.94 | G12: =PROPER(TRIM(CLEAN(_xlfn.XLOOKUP(Order_Items_Raw!A125,Orders_Raw!A:A,Orders_Raw!E:E)))) -> Website | H12: =_xlfn.XLOOKUP(B12,Products_Raw!A:A,Products_Raw!C:C) -> Sports | I12: =_xlfn.XLOOKUP(_xlfn.XLOOKUP(A12,Orders_Raw!A:A,Orders_Raw!B:B),Customers_Raw!A:A,Customers_Raw!E:E) -> Corporate | J12: =_xlfn.XLOOKUP(Order_Items_Raw!A125,Orders_Raw!A:A,Orders_Raw!C:C) -> 45757 | K12: Apr | L12: =_xlfn.XLOOKUP(A12,Orders_Raw!A:A,Orders_Raw!D:D) -> Shipped | M12: =_xlfn.XLOOKUP(_xlfn.XLOOKUP(A12,Orders_Raw!A:A,Orders_Raw!B:B),Customers_Raw!A:A,Customers_Raw!E:E) -> Corporate | N12: =IF(COUNTIF($A$2:A12,A12)=1,1,0) -> 1
A13: O51806 | B13: P1003 | C13: 2 | D13: 12184.13 | E13: =_xlfn.XLOOKUP(Order_Items_Raw!B127,Products_Raw!A:A,Products_Raw!D:D) -> 1349.93 | F13: =D13-(C13*E13) -> 9484.27 | G13: =PROPER(TRIM(CLEAN(_xlfn.XLOOKUP(Order_Items_Raw!A127,Orders_Raw!A:A,Orders_Raw!E:E)))) -> Website | H13: =_xlfn.XLOOKUP(B13,Products_Raw!A:A,Products_Raw!C:C) -> Sports | I13: =_xlfn.XLOOKUP(_xlfn.XLOOKUP(A13,Orders_Raw!A:A,Orders_Raw!B:B),Customers_Raw!A:A,Customers_Raw!E:E) -> Consumer | J13: =_xlfn.XLOOKUP(Order_Items_Raw!A127,Orders_Raw!A:A,Orders_Raw!C:C) -> 45764 | K13: Apr | L13: =_xlfn.XLOOKUP(A13,Orders_Raw!A:A,Orders_Raw!D:D) -> Delivered | M13: =_xlfn.XLOOKUP(_xlfn.XLOOKUP(A13,Orders_Raw!A:A,Orders_Raw!B:B),Customers_Raw!A:A,Customers_Raw!E:E) -> Consumer | N13: =IF(COUNTIF($A$2:A13,A13)=1,1,0) -> 1
A14: O50152 | B14: P1004 | C14: 1 | D14: 1748.61 | E14: =_xlfn.XLOOKUP(Order_Items_Raw!B141,Products_Raw!A:A,Products_Raw!D:D) -> 6443.36 | F14: =D14-(C14*E14) -> -4694.75 | G14: =PROPER(TRIM(CLEAN(_xlfn.XLOOKUP(Order_Items_Raw!A141,Orders_Raw!A:A,Orders_Raw!E:E)))) -> Mobile App | H14: =_xlfn.XLOOKUP(B14,Products_Raw!A:A,Products_Raw!C:C) -> Beauty | I14: =_xlfn.XLOOKUP(_xlfn.XLOOKUP(A14,Orders_Raw!A:A,Orders_Raw!B:B),Customers_Raw!A:A,Customers_Raw!E:E) -> Consumer | J14: =_xlfn.XLOOKUP(Order_Items_Raw!A141,Orders_Raw!A:A,Orders_Raw!C:C) -> 45773 | K14: Apr | L14: =_xlfn.XLOOKUP(A14,Orders_Raw!A:A,Orders_Raw!D:D) -> Delivered | M14: =_xlfn.XLOOKUP(_xlfn.XLOOKUP(A14,Orders_Raw!A:A,Orders_Raw!B:B),Customers_Raw!A:A,Customers_Raw!E:E) -> Consumer | N14: =IF(COUNTIF($A$2:A14,A14)=1,1,0) -> 1
A15: O50310 | B15: P1004 | C15: 2 | D15: 2617.46 | E15: =_xlfn.XLOOKUP(Order_Items_Raw!B145,Products_Raw!A:A,Products_Raw!D:D) -> 10124.42 | F15: =D15-(C15*E15) -> -17631.38 | G15: =PROPER(TRIM(CLEAN(_xlfn.XLOOKUP(Order_Items_Raw!A145,Orders_Raw!A:A,Orders_Raw!E:E)))) -> Mobile App | H15: =_xlfn.XLOOKUP(B15,Products_Raw!A:A,Products_Raw!C:C) -> Beauty | I15: =_xlfn.XLOOKUP(_xlfn.XLOOKUP(A15,Orders_Raw!A:A,Orders_Raw!B:B),Customers_Raw!A:A,Customers_Raw!E:E) -> Small Business | J15: =_xlfn.XLOOKUP(Order_Items_Raw!A145,Orders_Raw!A:A,Orders_Raw!C:C) -> 45771 | K15: Apr | L15: =_xlfn.XLOOKUP(A15,Orders_Raw!A:A,Orders_Raw!D:D) -> Delivered | M15: =_xlfn.XLOOKUP(_xlfn.XLOOKUP(A15,Orders_Raw!A:A,Orders_Raw!B:B),Customers_Raw!A:A,Customers_Raw!E:E) -> Small Business | N15: =IF(COUNTIF($A$2:A15,A15)=1,1,0) -> 1
A16: O51177 | B16: P1004 | C16: 1 | D16: 1455.44 | E16: =_xlfn.XLOOKUP(Order_Items_Raw!B158,Products_Raw!A:A,Products_Raw!D:D) -> 1397.32 | F16: =D16-(C16*E16) -> 58.12 | G16: =PROPER(TRIM(CLEAN(_xlfn.XLOOKUP(Order_Items_Raw!A158,Orders_Raw!A:A,Orders_Raw!E:E)))) -> Mobile App | H16: =_xlfn.XLOOKUP(B16,Products_Raw!A:A,Products_Raw!C:C) -> Beauty | I16: =_xlfn.XLOOKUP(_xlfn.XLOOKUP(A16,Orders_Raw!A:A,Orders_Raw!B:B),Customers_Raw!A:A,Customers_Raw!E:E) -> Consumer | J16: =_xlfn.XLOOKUP(Order_Items_Raw!A158,Orders_Raw!A:A,Orders_Raw!C:C) -> 45774 | K16: Apr | L16: =_xlfn.XLOOKUP(A16,Orders_Raw!A:A,Orders_Raw!D:D) -> Delivered | M16: =_xlfn.XLOOKUP(_xlfn.XLOOKUP(A16,Orders_Raw!A:A,Orders_Raw!B:B),Customers_Raw!A:A,Customers_Raw!E:E) -> Consumer | N16: =IF(COUNTIF($A$2:A16,A16)=1,1,0) -> 1
A17: O52217 | B17: P1004 | C17: 3 | D17: 4073.11 | E17: =_xlfn.XLOOKUP(Order_Items_Raw!B176,Products_Raw!A:A,Products_Raw!D:D) -> 2857.57 | F17: =D17-(C17*E17) -> -4499.6 | G17: =PROPER(TRIM(CLEAN(_xlfn.XLOOKUP(Order_Items_Raw!A176,Orders_Raw!A:A,Orders_Raw!E:E)))) -> Mobile App | H17: =_xlfn.XLOOKUP(B17,Products_Raw!A:A,Products_Raw!C:C) -> Beauty | I17: =_xlfn.XLOOKUP(_xlfn.XLOOKUP(A17,Orders_Raw!A:A,Orders_Raw!B:B),Customers_Raw!A:A,Customers_Raw!E:E) -> Consumer | J17: =_xlfn.XLOOKUP(Order_Items_Raw!A176,Orders_Raw!A:A,Orders_Raw!C:C) -> 45771 | K17: Apr | L17: =_xlfn.XLOOKUP(A17,Orders_Raw!A:A,Orders_Raw!D:D) -> Delivered | M17: =_xlfn.XLOOKUP(_xlfn.XLOOKUP(A17,Orders_Raw!A:A,Orders_Raw!B:B),Customers_Raw!A:A,Customers_Raw!E:E) -> Consumer | N17: =IF(COUNTIF($A$2:A17,A17)=1,1,0) -> 1
A18: O50871 | B18: P1005 | C18: 4 | D18: 42137.63 | E18: =_xlfn.XLOOKUP(Order_Items_Raw!B202,Products_Raw!A:A,Products_Raw!D:D) -> 11118.8 | F18: =D18-(C18*E18) -> -2337.57 | G18: =PROPER(TRIM(CLEAN(_xlfn.XLOOKUP(Order_Items_Raw!A202,Orders_Raw!A:A,Orders_Raw!E:E)))) -> Marketplace | H18: =_xlfn.XLOOKUP(B18,Products_Raw!A:A,Products_Raw!C:C) -> Sports | I18: =_xlfn.XLOOKUP(_xlfn.XLOOKUP(A18,Orders_Raw!A:A,Orders_Raw!B:B),Customers_Raw!A:A,Customers_Raw!E:E) -> Consumer | J18: =_xlfn.XLOOKUP(Order_Items_Raw!A202,Orders_Raw!A:A,Orders_Raw!C:C) -> 45773 | K18: Apr | L18: =_xlfn.XLOOKUP(A18,Orders_Raw!A:A,Orders_Raw!D:D) -> Shipped | M18: =_xlfn.XLOOKUP(_xlfn.XLOOKUP(A18,Orders_Raw!A:A,Orders_Raw!B:B),Customers_Raw!A:A,Customers_Raw!E:E) -> Consumer | N18: =IF(COUNTIF($A$2:A18,A18)=1,1,0) -> 1
A19: O52314 | B19: P1005 | C19: 4 | D19: 30423.76 | E19: =_xlfn.XLOOKUP(Order_Items_Raw!B236,Products_Raw!A:A,Products_Raw!D:D) -> 5412.91 | F19: =D19-(C19*E19) -> 8772.12 | G19: =PROPER(TRIM(CLEAN(_xlfn.XLOOKUP(Order_Items_Raw!A236,Orders_Raw!A:A,Orders_Raw!E:E)))) -> Marketplace | H19: =_xlfn.XLOOKUP(B19,Products_Raw!A:A,Products_Raw!C:C) -> Sports | I19: =_xlfn.XLOOKUP(_xlfn.XLOOKUP(A19,Orders_Raw!A:A,Orders_Raw!B:B),Customers_Raw!A:A,Customers_Raw!E:E) -> Corporate | J19: =_xlfn.XLOOKUP(Order_Items_Raw!A236,Orders_Raw!A:A,Orders_Raw!C:C) -> 45773 | K19: Apr | L19: =_xlfn.XLOOKUP(A19,Orders_Raw!A:A,Orders_Raw!D:D) -> Processing | M19: =_xlfn.XLOOKUP(_xlfn.XLOOKUP(A19,Orders_Raw!A:A,Orders_Raw!B:B),Customers_Raw!A:A,Customers_Raw!E:E) -> Corporate | N19: =IF(COUNTIF($A$2:A19,A19)=1,1,0) -> 1
A20: O50095 | B20: P1006 | C20: 2 | D20: 31478.26 | E20: =_xlfn.XLOOKUP(Order_Items_Raw!B240,Products_Raw!A:A,Products_Raw!D:D) -> 5412.91 | F20: =D20-(C20*E20) -> 20652.44 | G20: =PROPER(TRIM(CLEAN(_xlfn.XLOOKUP(Order_Items_Raw!A240,Orders_Raw!A:A,Orders_Raw!E:E)))) -> Website | H20: =_xlfn.XLOOKUP(B20,Products_Raw!A:A,Products_Raw!C:C) -> Electronics | I20: =_xlfn.XLOOKUP(_xlfn.XLOOKUP(A20,Orders_Raw!A:A,Orders_Raw!B:B),Customers_Raw!A:A,Customers_Raw!E:E) -> Corporate | J20: =_xlfn.XLOOKUP(Order_Items_Raw!A240,Orders_Raw!A:A,Orders_Raw!C:C) -> 45751 | K20: Apr | L20: =_xlfn.XLOOKUP(A20,Orders_Raw!A:A,Orders_Raw!D:D) -> Cancelled | M20: =_xlfn.XLOOKUP(_xlfn.XLOOKUP(A20,Orders_Raw!A:A,Orders_Raw!B:B),Customers_Raw!A:A,Customers_Raw!E:E) -> Corporate | N20: =IF(COUNTIF($A$2:A20,A20)=1,1,0) -> 1
A21: O50165 | B21: P1006 | C21: 1 | D21: 12976.25 | E21: =_xlfn.XLOOKUP(Order_Items_Raw!B242,Products_Raw!A:A,Products_Raw!D:D) -> 5412.91 | F21: =D21-(C21*E21) -> 7563.34 | G21: =PROPER(TRIM(CLEAN(_xlfn.XLOOKUP(Order_Items_Raw!A242,Orders_Raw!A:A,Orders_Raw!E:E)))) -> Mobile App | H21: =_xlfn.XLOOKUP(B21,Products_Raw!A:A,Products_Raw!C:C) -> Electronics | I21: =_xlfn.XLOOKUP(_xlfn.XLOOKUP(A21,Orders_Raw!A:A,Orders_Raw!B:B),Customers_Raw!A:A,Customers_Raw!E:E) -> Consumer | J21: =_xlfn.XLOOKUP(Order_Items_Raw!A242,Orders_Raw!A:A,Orders_Raw!C:C) -> 45776 | K21: Apr | L21: =_xlfn.XLOOKUP(A21,Orders_Raw!A:A,Orders_Raw!D:D) -> Delivered | M21: =_xlfn.XLOOKUP(_xlfn.XLOOKUP(A21,Orders_Raw!A:A,Orders_Raw!B:B),Customers_Raw!A:A,Customers_Raw!E:E) -> Consumer | N21: =IF(COUNTIF($A$2:A21,A21)=1,1,0) -> 1
A22: O51913 | B22: P1006 | C22: 4 | D22: 55018.66 | E22: =_xlfn.XLOOKUP(Order_Items_Raw!B268,Products_Raw!A:A,Products_Raw!D:D) -> 11653.29 | F22: =D22-(C22*E22) -> 8405.5 | G22: =PROPER(TRIM(CLEAN(_xlfn.XLOOKUP(Order_Items_Raw!A268,Orders_Raw!A:A,Orders_Raw!E:E)))) -> Website | H22: =_xlfn.XLOOKUP(B22,Products_Raw!A:A,Products_Raw!C:C) -> Electronics | I22: =_xlfn.XLOOKUP(_xlfn.XLOOKUP(A22,Orders_Raw!A:A,Orders_Raw!B:B),Customers_Raw!A:A,Customers_Raw!E:E) -> Consumer | J22: =_xlfn.XLOOKUP(Order_Items_Raw!A268,Orders_Raw!A:A,Orders_Raw!C:C) -> 45766 | K22: Apr | L22: =_xlfn.XLOOKUP(A22,Orders_Raw!A:A,Orders_Raw!D:D) -> Delivered | M22: =_xlfn.XLOOKUP(_xlfn.XLOOKUP(A22,Orders_Raw!A:A,Orders_Raw!B:B),Customers_Raw!A:A,Customers_Raw!E:E) -> Consumer | N22: =IF(COUNTIF($A$2:A22,A22)=1,1,0) -> 1
A23: O52296 | B23: P1006 | C23: 2 | D23: 25394.77 | E23: =_xlfn.XLOOKUP(Order_Items_Raw!B277,Products_Raw!A:A,Products_Raw!D:D) -> 11764.29 | F23: =D23-(C23*E23) -> 1866.19 | G23: =PROPER(TRIM(CLEAN(_xlfn.XLOOKUP(Order_Items_Raw!A277,Orders_Raw!A:A,Orders_Raw!E:E)))) -> Mobile App | H23: =_xlfn.XLOOKUP(B23,Products_Raw!A:A,Products_Raw!C:C) -> Electronics | I23: =_xlfn.XLOOKUP(_xlfn.XLOOKUP(A23,Orders_Raw!A:A,Orders_Raw!B:B),Customers_Raw!A:A,Customers_Raw!E:E) -> Consumer | J23: =_xlfn.XLOOKUP(Order_Items_Raw!A277,Orders_Raw!A:A,Orders_Raw!C:C) -> 45760 | K23: Apr | L23: =_xlfn.XLOOKUP(A23,Orders_Raw!A:A,Orders_Raw!D:D) -> Processing | M23: =_xlfn.XLOOKUP(_xlfn.XLOOKUP(A23,Orders_Raw!A:A,Orders_Raw!B:B),Customers_Raw!A:A,Customers_Raw!E:E) -> Consumer | N23: =IF(COUNTIF($A$2:A23,A23)=1,1,0) -> 1
A24: O50871 | B24: P1007 | C24: 3 | D24: 30108.57 | E24: =_xlfn.XLOOKUP(Order_Items_Raw!B296,Products_Raw!A:A,Products_Raw!D:D) -> 10086.81 | F24: =D24-(C24*E24) -> -151.86 | G24: =PROPER(TRIM(CLEAN(_xlfn.XLOOKUP(Order_Items_Raw!A296,Orders_Raw!A:A,Orders_Raw!E:E)))) -> Mobile App | H24: =_xlfn.XLOOKUP(B24,Products_Raw!A:A,Products_Raw!C:C) -> Sports | I24: =_xlfn.XLOOKUP(_xlfn.XLOOKUP(A24,Orders_Raw!A:A,Orders_Raw!B:B),Customers_Raw!A:A,Customers_Raw!E:E) -> Consumer | J24: =_xlfn.XLOOKUP(Order_Items_Raw!A296,Orders_Raw!A:A,Orders_Raw!C:C) -> 45758 | K24: Apr | L24: =_xlfn.XLOOKUP(A24,Orders_Raw!A:A,Orders_Raw!D:D) -> Shipped | M24: =_xlfn.XLOOKUP(_xlfn.XLOOKUP(A24,Orders_Raw!A:A,Orders_Raw!B:B),Customers_Raw!A:A,Customers_Raw!E:E) -> Consumer | N24: =IF(COUNTIF($A$2:A24,A24)=1,1,0) -> 0
A25: O51082 | B25: P1007 | C25: 4 | D25: 35924.35 | E25: =_xlfn.XLOOKUP(Order_Items_Raw!B304,Products_Raw!A:A,Products_Raw!D:D) -> 9947.76 | F25: =D25-(C25*E25) -> -3866.69 | G25: =PROPER(TRIM(CLEAN(_xlfn.XLOOKUP(Order_Items_Raw!A304,Orders_Raw!A:A,Orders_Raw!E:E)))) -> Mobile App | H25: =_xlfn.XLOOKUP(B25,Products_Raw!A:A,Products_Raw!C:C) -> Sports | I25: =_xlfn.XLOOKUP(_xlfn.XLOOKUP(A25,Orders_Raw!A:A,Orders_Raw!B:B),Customers_Raw!A:A,Customers_Raw!E:E) -> Consumer | J25: =_xlfn.XLOOKUP(Order_Items_Raw!A304,Orders_Raw!A:A,Orders_Raw!C:C) -> 45758 | K25: Apr | L25: =_xlfn.XLOOKUP(A25,Orders_Raw!A:A,Orders_Raw!D:D) -> Delivered | M25: =_xlfn.XLOOKUP(_xlfn.XLOOKUP(A25,Orders_Raw!A:A,Orders_Raw!B:B),Customers_Raw!A:A,Customers_Raw!E:E) -> Consumer | N25: =IF(COUNTIF($A$2:A25,A25)=1,1,0) -> 1
A26: O50611 | B26: P1009 | C26: 4 | D26: 23277.91 | E26: =_xlfn.XLOOKUP(Order_Items_Raw!B388,Products_Raw!A:A,Products_Raw!D:D) -> 295.87 | F26: =D26-(C26*E26) -> 22094.43 | G26: =PROPER(TRIM(CLEAN(_xlfn.XLOOKUP(Order_Items_Raw!A388,Orders_Raw!A:A,Orders_Raw!E:E)))) -> Website | H26: =_xlfn.XLOOKUP(B26,Products_Raw!A:A,Products_Raw!C:C) -> Beauty | I26: =_xlfn.XLOOKUP(_xlfn.XLOOKUP(A26,Orders_Raw!A:A,Orders_Raw!B:B),Customers_Raw!A:A,Customers_Raw!E:E) -> Consumer | J26: =_xlfn.XLOOKUP(Order_Items_Raw!A388,Orders_Raw!A:A,Orders_Raw!C:C) -> 45886 | K26: Aug | L26: =_xlfn.XLOOKUP(A26,Orders_Raw!A:A,Orders_Raw!D:D) -> Delivered | M26: =_xlfn.XLOOKUP(_xlfn.XLOOKUP(A26,Orders_Raw!A:A,Orders_Raw!B:B),Customers_Raw!A:A,Customers_Raw!E:E) -> Consumer | N26: =IF(COUNTIF($A$2:A26,A26)=1,1,0) -> 1
A27: O51045 | B27: P1009 | C27: 3 | D27: 20547.71 | E27: =_xlfn.XLOOKUP(Order_Items_Raw!B395,Products_Raw!A:A,Products_Raw!D:D) -> 295.87 | F27: =D27-(C27*E27) -> 19660.1 | G27: =PROPER(TRIM(CLEAN(_xlfn.XLOOKUP(Order_Items_Raw!A395,Orders_Raw!A:A,Orders_Raw!E:E)))) -> Website | H27: =_xlfn.XLOOKUP(B27,Products_Raw!A:A,Products_Raw!C:C) -> Beauty | I27: =_xlfn.XLOOKUP(_xlfn.XLOOKUP(A27,Orders_Raw!A:A,Orders_Raw!B:B),Customers_Raw!A:A,Customers_Raw!E:E) -> Consumer | J27: =_xlfn.XLOOKUP(Order_Items_Raw!A395,Orders_Raw!A:A,Orders_Raw!C:C) -> 45894 | K27: Aug | L27: =_xlfn.XLOOKUP(A27,Orders_Raw!A:A,Orders_Raw!D:D) -> Delivered | M27: =_xlfn.XLOOKUP(_xlfn.XLOOKUP(A27,Orders_Raw!A:A,Orders_Raw!B:B),Customers_Raw!A:A,Customers_Raw!E:E) -> Consumer | N27: =IF(COUNTIF($A$2:A27,A27)=1,1,0) -> 1
A28: O51194 | B28: P1009 | C28: 1 | D28: 6055.99 | E28: =_xlfn.XLOOKUP(Order_Items_Raw!B400,Products_Raw!A:A,Products_Raw!D:D) -> 474.93 | F28: =D28-(C28*E28) -> 5581.06 | G28: =PROPER(TRIM(CLEAN(_xlfn.XLOOKUP(Order_Items_Raw!A400,Orders_Raw!A:A,Orders_Raw!E:E)))) -> Website | H28: =_xlfn.XLOOKUP(B28,Products_Raw!A:A,Products_Raw!C:C) -> Beauty | I28: =_xlfn.XLOOKUP(_xlfn.XLOOKUP(A28,Orders_Raw!A:A,Orders_Raw!B:B),Customers_Raw!A:A,Customers_Raw!E:E) -> Corporate | J28: =_xlfn.XLOOKUP(Order_Items_Raw!A400,Orders_Raw!A:A,Orders_Raw!C:C) -> 45888 | K28: Aug | L28: =_xlfn.XLOOKUP(A28,Orders_Raw!A:A,Orders_Raw!D:D) -> Delivered | M28: =_xlfn.XLOOKUP(_xlfn.XLOOKUP(A28,Orders_Raw!A:A,Orders_Raw!B:B),Customers_Raw!A:A,Customers_Raw!E:E) -> Corporate | N28: =IF(COUNTIF($A$2:A28,A28)=1,1,0) -> 1
A29: O50337 | B29: P1010 | C29: 1 | D29: 7902.31 | E29: =_xlfn.XLOOKUP(Order_Items_Raw!B428,Products_Raw!A:A,Products_Raw!D:D) -> 7802.03 | F29: =D29-(C29*E29) -> 100.28 | G29: =PROPER(TRIM(CLEAN(_xlfn.XLOOKUP(Order_Items_Raw!A428,Orders_Raw!A:A,Orders_Raw!E:E)))) -> Marketplace | H29: =_xlfn.XLOOKUP(B29,Products_Raw!A:A,Products_Raw!C:C) -> Home & Kitchen | I29: =_xlfn.XLOOKUP(_xlfn.XLOOKUP(A29,Orders_Raw!A:A,Orders_Raw!B:B),Customers_Raw!A:A,Customers_Raw!E:E) -> Small Business | J29: =_xlfn.XLOOKUP(Order_Items_Raw!A428,Orders_Raw!A:A,Orders_Raw!C:C) -> 45883 | K29: Aug | L29: =_xlfn.XLOOKUP(A29,Orders_Raw!A:A,Orders_Raw!D:D) -> Delivered | M29: =_xlfn.XLOOKUP(_xlfn.XLOOKUP(A29,Orders_Raw!A:A,Orders_Raw!B:B),Customers_Raw!A:A,Customers_Raw!E:E) -> Small Business | N29: =IF(COUNTIF($A$2:A29,A29)=1,1,0) -> 1
A30: O50462 | B30: P1010 | C30: 4 | D30: 34520.55 | E30: =_xlfn.XLOOKUP(Order_Items_Raw!B431,Products_Raw!A:A,Products_Raw!D:D) -> 680.62 | F30: =D30-(C30*E30) -> 31798.07 | G30: =PROPER(TRIM(CLEAN(_xlfn.XLOOKUP(Order_Items_Raw!A431,Orders_Raw!A:A,Orders_Raw!E:E)))) -> Website | H30: =_xlfn.XLOOKUP(B30,Products_Raw!A:A,Products_Raw!C:C) -> Home & Kitchen | I30: =_xlfn.XLOOKUP(_xlfn.XLOOKUP(A30,Orders_Raw!A:A,Orders_Raw!B:B),Customers_Raw!A:A,Customers_Raw!E:E) -> Small Business | J30: =_xlfn.XLOOKUP(Order_Items_Raw!A431,Orders_Raw!A:A,Orders_Raw!C:C) -> 45886 | K30: Aug | L30: =_xlfn.XLOOKUP(A30,Orders_Raw!A:A,Orders_Raw!D:D) -> Shipped | M30: =_xlfn.XLOOKUP(_xlfn.XLOOKUP(A30,Orders_Raw!A:A,Orders_Raw!B:B),Customers_Raw!A:A,Customers_Raw!E:E) -> Small Business | N30: =IF(COUNTIF($A$2:A30,A30)=1,1,0) -> 1
A31: O51410 | B31: P1010 | C31: 3 | D31: 19236.47 | E31: =_xlfn.XLOOKUP(Order_Items_Raw!B449,Products_Raw!A:A,Products_Raw!D:D) -> 4640.09 | F31: =D31-(C31*E31) -> 5316.2 | G31: =PROPER(TRIM(CLEAN(_xlfn.XLOOKUP(Order_Items_Raw!A449,Orders_Raw!A:A,Orders_Raw!E:E)))) -> Website | H31: =_xlfn.XLOOKUP(B31,Products_Raw!A:A,Products_Raw!C:C) -> Home & Kitchen | I31: =_xlfn.XLOOKUP(_xlfn.XLOOKUP(A31,Orders_Raw!A:A,Orders_Raw!B:B),Customers_Raw!A:A,Customers_Raw!E:E) -> Consumer | J31: =_xlfn.XLOOKUP(Order_Items_Raw!A449,Orders_Raw!A:A,Orders_Raw!C:C) -> 45900 | K31: Aug | L31: =_xlfn.XLOOKUP(A31,Orders_Raw!A:A,Orders_Raw!D:D) -> Processing | M31: =_xlfn.XLOOKUP(_xlfn.XLOOKUP(A31,Orders_Raw!A:A,Orders_Raw!B:B),Customers_Raw!A:A,Customers_Raw!E:E) -> Consumer | N31: =IF(COUNTIF($A$2:A31,A31)=1,1,0) -> 1
A32: O51690 | B32: P1010 | C32: 1 | D32: 6688.83 | E32: =_xlfn.XLOOKUP(Order_Items_Raw!B455,Products_Raw!A:A,Products_Raw!D:D) -> 229.52 | F32: =D32-(C32*E32) -> 6459.31 | G32: =PROPER(TRIM(CLEAN(_xlfn.XLOOKUP(Order_Items_Raw!A455,Orders_Raw!A:A,Orders_Raw!E:E)))) -> Marketplace | H32: =_xlfn.XLOOKUP(B32,Products_Raw!A:A,Products_Raw!C:C) -> Home & Kitchen | I32: =_xlfn.XLOOKUP(_xlfn.XLOOKUP(A32,Orders_Raw!A:A,Orders_Raw!B:B),Customers_Raw!A:A,Customers_Raw!E:E) -> Consumer | J32: =_xlfn.XLOOKUP(Order_Items_Raw!A455,Orders_Raw!A:A,Orders_Raw!C:C) -> 45897 | K32: Aug | L32: =_xlfn.XLOOKUP(A32,Orders_Raw!A:A,Orders_Raw!D:D) -> Shipped | M32: =_xlfn.XLOOKUP(_xlfn.XLOOKUP(A32,Orders_Raw!A:A,Orders_Raw!B:B),Customers_Raw!A:A,Customers_Raw!E:E) -> Consumer | N32: =IF(COUNTIF($A$2:A32,A32)=1,1,0) -> 1
A33: O50407 | B33: P1011 | C33: 3 | D33: 30937.85 | E33: =_xlfn.XLOOKUP(Order_Items_Raw!B476,Products_Raw!A:A,Products_Raw!D:D) -> 6443.36 | F33: =D33-(C33*E33) -> 11607.77 | G33: =PROPER(TRIM(CLEAN(_xlfn.XLOOKUP(Order_Items_Raw!A476,Orders_Raw!A:A,Orders_Raw!E:E)))) -> Website | H33: =_xlfn.XLOOKUP(B33,Products_Raw!A:A,Products_Raw!C:C) -> Sports | I33: =_xlfn.XLOOKUP(_xlfn.XLOOKUP(A33,Orders_Raw!A:A,Orders_Raw!B:B),Customers_Raw!A:A,Customers_Raw!E:E) -> Consumer | J33: =_xlfn.XLOOKUP(Order_Items_Raw!A476,Orders_Raw!A:A,Orders_Raw!C:C) -> 45896 | K33: Aug | L33: =_xlfn.XLOOKUP(A33,Orders_Raw!A:A,Orders_Raw!D:D) -> Delivered | M33: =_xlfn.XLOOKUP(_xlfn.XLOOKUP(A33,Orders_Raw!A:A,Orders_Raw!B:B),Customers_Raw!A:A,Customers_Raw!E:E) -> Consumer | N33: =IF(COUNTIF($A$2:A33,A33)=1,1,0) -> 1
A34: O51403 | B34: P1011 | C34: 1 | D34: 8446.75 | E34: =_xlfn.XLOOKUP(Order_Items_Raw!B502,Products_Raw!A:A,Products_Raw!D:D) -> 11668.5 | F34: =D34-(C34*E34) -> -3221.75 | G34: =PROPER(TRIM(CLEAN(_xlfn.XLOOKUP(Order_Items_Raw!A502,Orders_Raw!A:A,Orders_Raw!E:E)))) -> Mobile App | H34: =_xlfn.XLOOKUP(B34,Products_Raw!A:A,Products_Raw!C:C) -> Sports | I34: =_xlfn.XLOOKUP(_xlfn.XLOOKUP(A34,Orders_Raw!A:A,Orders_Raw!B:B),Customers_Raw!A:A,Customers_Raw!E:E) -> Consumer | J34: =_xlfn.XLOOKUP(Order_Items_Raw!A502,Orders_Raw!A:A,Orders_Raw!C:C) -> 45887 | K34: Aug | L34: =_xlfn.XLOOKUP(A34,Orders_Raw!A:A,Orders_Raw!D:D) -> Delivered | M34: =_xlfn.XLOOKUP(_xlfn.XLOOKUP(A34,Orders_Raw!A:A,Orders_Raw!B:B),Customers_Raw!A:A,Customers_Raw!E:E) -> Consumer | N34: =IF(COUNTIF($A$2:A34,A34)=1,1,0) -> 1
A35: O50565 | B35: P1012 | C35: 3 | D35: 36246.91 | E35: =_xlfn.XLOOKUP(Order_Items_Raw!B531,Products_Raw!A:A,Products_Raw!D:D) -> 11118.8 | F35: =D35-(C35*E35) -> 2890.51 | G35: =PROPER(TRIM(CLEAN(_xlfn.XLOOKUP(Order_Items_Raw!A531,Orders_Raw!A:A,Orders_Raw!E:E)))) -> Website | H35: =_xlfn.XLOOKUP(B35,Products_Raw!A:A,Products_Raw!C:C) -> Electronics | I35: =_xlfn.XLOOKUP(_xlfn.XLOOKUP(A35,Orders_Raw!A:A,Orders_Raw!B:B),Customers_Raw!A:A,Customers_Raw!E:E) -> Corporate | J35: =_xlfn.XLOOKUP(Order_Items_Raw!A531,Orders_Raw!A:A,Orders_Raw!C:C) -> 45885 | K35: Aug | L35: =_xlfn.XLOOKUP(A35,Orders_Raw!A:A,Orders_Raw!D:D) -> Shipped | M35: =_xlfn.XLOOKUP(_xlfn.XLOOKUP(A35,Orders_Raw!A:A,Orders_Raw!B:B),Customers_Raw!A:A,Customers_Raw!E:E) -> Corporate | N35: =IF(COUNTIF($A$2:A35,A35)=1,1,0) -> 1
A36: O50633 | B36: P1012 | C36: 3 | D36: 40026.98 | E36: =_xlfn.XLOOKUP(Order_Items_Raw!B533,Products_Raw!A:A,Products_Raw!D:D) -> 5057.68 | F36: =D36-(C36*E36) -> 24853.94 | G36: =PROPER(TRIM(CLEAN(_xlfn.XLOOKUP(Order_Items_Raw!A533,Orders_Raw!A:A,Orders_Raw!E:E)))) -> Mobile App | H36: =_xlfn.XLOOKUP(B36,Products_Raw!A:A,Products_Raw!C:C) -> Electronics | I36: =_xlfn.XLOOKUP(_xlfn.XLOOKUP(A36,Orders_Raw!A:A,Orders_Raw!B:B),Customers_Raw!A:A,Customers_Raw!E:E) -> Corporate | J36: =_xlfn.XLOOKUP(Order_Items_Raw!A533,Orders_Raw!A:A,Orders_Raw!C:C) -> 45895 | K36: Aug | L36: =_xlfn.XLOOKUP(A36,Orders_Raw!A:A,Orders_Raw!D:D) -> Delivered | M36: =_xlfn.XLOOKUP(_xlfn.XLOOKUP(A36,Orders_Raw!A:A,Orders_Raw!B:B),Customers_Raw!A:A,Customers_Raw!E:E) -> Corporate | N36: =IF(COUNTIF($A$2:A36,A36)=1,1,0) -> 1
A37: O51129 | B37: P1012 | C37: 1 | D37: 14657.97 | E37: =_xlfn.XLOOKUP(Order_Items_Raw!B542,Products_Raw!A:A,Products_Raw!D:D) -> 1892.68 | F37: =D37-(C37*E37) -> 12765.29 | G37: =PROPER(TRIM(CLEAN(_xlfn.XLOOKUP(Order_Items_Raw!A542,Orders_Raw!A:A,Orders_Raw!E:E)))) -> Mobile App | H37: =_xlfn.XLOOKUP(B37,Products_Raw!A:A,Products_Raw!C:C) -> Electronics | I37: =_xlfn.XLOOKUP(_xlfn.XLOOKUP(A37,Orders_Raw!A:A,Orders_Raw!B:B),Customers_Raw!A:A,Customers_Raw!E:E) -> Corporate | J37: =_xlfn.XLOOKUP(Order_Items_Raw!A542,Orders_Raw!A:A,Orders_Raw!C:C) -> 45876 | K37: Aug | L37: =_xlfn.XLOOKUP(A37,Orders_Raw!A:A,Orders_Raw!D:D) -> Delivered | M37: =_xlfn.XLOOKUP(_xlfn.XLOOKUP(A37,Orders_Raw!A:A,Orders_Raw!B:B),Customers_Raw!A:A,Customers_Raw!E:E) -> Corporate | N37: =IF(COUNTIF($A$2:A37,A37)=1,1,0) -> 1
A38: O51425 | B38: P1012 | C38: 2 | D38: 24755.1 | E38: =_xlfn.XLOOKUP(Order_Items_Raw!B550,Products_Raw!A:A,Products_Raw!D:D) -> 5931.04 | F38: =D38-(C38*E38) -> 12893.02 | G38: =PROPER(TRIM(CLEAN(_xlfn.XLOOKUP(Order_Items_Raw!A550,Orders_Raw!A:A,Orders_Raw!E:E)))) -> Marketplace | H38: =_xlfn.XLOOKUP(B38,Products_Raw!A:A,Products_Raw!C:C) -> Electronics | I38: =_xlfn.XLOOKUP(_xlfn.XLOOKUP(A38,Orders_Raw!A:A,Orders_Raw!B:B),Customers_Raw!A:A,Customers_Raw!E:E) -> Consumer | J38: =_xlfn.XLOOKUP(Order_Items_Raw!A550,Orders_Raw!A:A,Orders_Raw!C:C) -> 45893 | K38: Aug | L38: =_xlfn.XLOOKUP(A38,Orders_Raw!A:A,Orders_Raw!D:D) -> Shipped | M38: =_xlfn.XLOOKUP(_xlfn.XLOOKUP(A38,Orders_Raw!A:A,Orders_Raw!B:B),Customers_Raw!A:A,Customers_Raw!E:E) -> Consumer | N38: =IF(COUNTIF($A$2:A38,A38)=1,1,0) -> 1
A39: O51717 | B39: P1012 | C39: 1 | D39: 10979.75 | E39: =_xlfn.XLOOKUP(Order_Items_Raw!B558,Products_Raw!A:A,Products_Raw!D:D) -> 4539.2 | F39: =D39-(C39*E39) -> 6440.55 | G39: =PROPER(TRIM(CLEAN(_xlfn.XLOOKUP(Order_Items_Raw!A558,Orders_Raw!A:A,Orders_Raw!E:E)))) -> Website | H39: =_xlfn.XLOOKUP(B39,Products_Raw!A:A,Products_Raw!C:C) -> Electronics | I39: =_xlfn.XLOOKUP(_xlfn.XLOOKUP(A39,Orders_Raw!A:A,Orders_Raw!B:B),Customers_Raw!A:A,Customers_Raw!E:E) -> Corporate | J39: =_xlfn.XLOOKUP(Order_Items_Raw!A558,Orders_Raw!A:A,Orders_Raw!C:C) -> 45878 | K39: Aug | L39: =_xlfn.XLOOKUP(A39,Orders_Raw!A:A,Orders_Raw!D:D) -> Shipped | M39: =_xlfn.XLOOKUP(_xlfn.XLOOKUP(A39,Orders_Raw!A:A,Orders_Raw!B:B),Customers_Raw!A:A,Customers_Raw!E:E) -> Corporate | N39: =IF(COUNTIF($A$2:A39,A39)=1,1,0) -> 0
A40: O51913 | B40: P1012 | C40: 4 | D40: 44612.51 | E40: =_xlfn.XLOOKUP(Order_Items_Raw!B560,Products_Raw!A:A,Products_Raw!D:D) -> 4591.42 | F40: =D40-(C40*E40) -> 26246.83 | G40: =PROPER(TRIM(CLEAN(_xlfn.XLOOKUP(Order_Items_Raw!A560,Orders_Raw!A:A,Orders_Raw!E:E)))) -> Mobile App | H40: =_xlfn.XLOOKUP(B40,Products_Raw!A:A,Products_Raw!C:C) -> Electronics | I40: =_xlfn.XLOOKUP(_xlfn.XLOOKUP(A40,Orders_Raw!A:A,Orders_Raw!B:B),Customers_Raw!A:A,Customers_Raw!E:E) -> Consumer | J40: =_xlfn.XLOOKUP(Order_Items_Raw!A560,Orders_Raw!A:A,Orders_Raw!C:C) -> 45877 | K40: Aug | L40: =_xlfn.XLOOKUP(A40,Orders_Raw!A:A,Orders_Raw!D:D) -> Delivered | M40: =_xlfn.XLOOKUP(_xlfn.XLOOKUP(A40,Orders_Raw!A:A,Orders_Raw!B:B),Customers_Raw!A:A,Customers_Raw!E:E) -> Consumer | N40: =IF(COUNTIF($A$2:A40,A40)=1,1,0) -> 0
A41: O52146 | B41: P1012 | C41: 3 | D41: 34002.04 | E41: =_xlfn.XLOOKUP(Order_Items_Raw!B564,Products_Raw!A:A,Products_Raw!D:D) -> 5766.98 | F41: =D41-(C41*E41) -> 16701.1 | G41: =PROPER(TRIM(CLEAN(_xlfn.XLOOKUP(Order_Items_Raw!A564,Orders_Raw!A:A,Orders_Raw!E:E)))) -> Website | H41: =_xlfn.XLOOKUP(B41,Products_Raw!A:A,Products_Raw!C:C) -> Electronics | I41: =_xlfn.XLOOKUP(_xlfn.XLOOKUP(A41,Orders_Raw!A:A,Orders_Raw!B:B),Customers_Raw!A:A,Customers_Raw!E:E) -> Consumer | J41: =_xlfn.XLOOKUP(Order_Items_Raw!A564,Orders_Raw!A:A,Orders_Raw!C:C) -> 45897 | K41: Aug | L41: =_xlfn.XLOOKUP(A41,Orders_Raw!A:A,Orders_Raw!D:D) -> Processing | M41: =_xlfn.XLOOKUP(_xlfn.XLOOKUP(A41,Orders_Raw!A:A,Orders_Raw!B:B),Customers_Raw!A:A,Customers_Raw!E:E) -> Consumer | N41: =IF(COUNTIF($A$2:A41,A41)=1,1,0) -> 0
A42: O52251 | B42: P1012 | C42: 4 | D42: 46502.36 | E42: =_xlfn.XLOOKUP(Order_Items_Raw!B566,Products_Raw!A:A,Products_Raw!D:D) -> 5766.98 | F42: =D42-(C42*E42) -> 23434.44 | G42: =PROPER(TRIM(CLEAN(_xlfn.XLOOKUP(Order_Items_Raw!A566,Orders_Raw!A:A,Orders_Raw!E:E)))) -> Mobile App | H42: =_xlfn.XLOOKUP(B42,Products_Raw!A:A,Products_Raw!C:C) -> Electronics | I42: =_xlfn.XLOOKUP(_xlfn.XLOOKUP(A42,Orders_Raw!A:A,Orders_Raw!B:B),Customers_Raw!A:A,Customers_Raw!E:E) -> Consumer | J42: =_xlfn.XLOOKUP(Order_Items_Raw!A566,Orders_Raw!A:A,Orders_Raw!C:C) -> 45895 | K42: Aug | L42: =_xlfn.XLOOKUP(A42,Orders_Raw!A:A,Orders_Raw!D:D) -> Delivered | M42: =_xlfn.XLOOKUP(_xlfn.XLOOKUP(A42,Orders_Raw!A:A,Orders_Raw!B:B),Customers_Raw!A:A,Customers_Raw!E:E) -> Consumer | N42: =IF(COUNTIF($A$2:A42,A42)=1,1,0) -> 1
A43: O50604 | B43: P1013 | C43: 3 | D43: 5428.28 | E43: =_xlfn.XLOOKUP(Order_Items_Raw!B579,Products_Raw!A:A,Products_Raw!D:D) -> 7341.5 | F43: =D43-(C43*E43) -> -16596.22 | G43: =PROPER(TRIM(CLEAN(_xlfn.XLOOKUP(Order_Items_Raw!A579,Orders_Raw!A:A,Orders_Raw!E:E)))) -> Website | H43: =_xlfn.XLOOKUP(B43,Products_Raw!A:A,Products_Raw!C:C) -> Office Supplies | I43: =_xlfn.XLOOKUP(_xlfn.XLOOKUP(A43,Orders_Raw!A:A,Orders_Raw!B:B),Customers_Raw!A:A,Customers_Raw!E:E) -> Consumer | J43: =_xlfn.XLOOKUP(Order_Items_Raw!A579,Orders_Raw!A:A,Orders_Raw!C:C) -> 45881 | K43: Aug | L43: =_xlfn.XLOOKUP(A43,Orders_Raw!A:A,Orders_Raw!D:D) -> Delivered | M43: =_xlfn.XLOOKUP(_xlfn.XLOOKUP(A43,Orders_Raw!A:A,Orders_Raw!B:B),Customers_Raw!A:A,Customers_Raw!E:E) -> Consumer | N43: =IF(COUNTIF($A$2:A43,A43)=1,1,0) -> 1
A44: O50891 | B44: P1013 | C44: 1 | D44: 2079.09 | E44: =_xlfn.XLOOKUP(Order_Items_Raw!B583,Products_Raw!A:A,Products_Raw!D:D) -> 1946.27 | F44: =D44-(C44*E44) -> 132.82 | G44: =PROPER(TRIM(CLEAN(_xlfn.XLOOKUP(Order_Items_Raw!A583,Orders_Raw!A:A,Orders_Raw!E:E)))) -> Website | H44: =_xlfn.XLOOKUP(B44,Products_Raw!A:A,Products_Raw!C:C) -> Office Supplies | I44: =_xlfn.XLOOKUP(_xlfn.XLOOKUP(A44,Orders_Raw!A:A,Orders_Raw!B:B),Customers_Raw!A:A,Customers_Raw!E:E) -> Consumer | J44: =_xlfn.XLOOKUP(Order_Items_Raw!A583,Orders_Raw!A:A,Orders_Raw!C:C) -> 45871 | K44: Aug | L44: =_xlfn.XLOOKUP(A44,Orders_Raw!A:A,Orders_Raw!D:D) -> Processing | M44: =_xlfn.XLOOKUP(_xlfn.XLOOKUP(A44,Orders_Raw!A:A,Orders_Raw!B:B),Customers_Raw!A:A,Customers_Raw!E:E) -> Consumer | N44: =IF(COUNTIF($A$2:A44,A44)=1,1,0) -> 1
A45: O52161 | B45: P1013 | C45: 4 | D45: 8666.64 | E45: =_xlfn.XLOOKUP(Order_Items_Raw!B603,Products_Raw!A:A,Products_Raw!D:D) -> 5812.86 | F45: =D45-(C45*E45) -> -14584.8 | G45: =PROPER(TRIM(CLEAN(_xlfn.XLOOKUP(Order_Items_Raw!A603,Orders_Raw!A:A,Orders_Raw!E:E)))) -> Marketplace | H45: =_xlfn.XLOOKUP(B45,Products_Raw!A:A,Products_Raw!C:C) -> Office Supplies | I45: =_xlfn.XLOOKUP(_xlfn.XLOOKUP(A45,Orders_Raw!A:A,Orders_Raw!B:B),Customers_Raw!A:A,Customers_Raw!E:E) -> Corporate | J45: =_xlfn.XLOOKUP(Order_Items_Raw!A603,Orders_Raw!A:A,Orders_Raw!C:C) -> 45889 | K45: Aug | L45: =_xlfn.XLOOKUP(A45,Orders_Raw!A:A,Orders_Raw!D:D) -> Delivered | M45: =_xlfn.XLOOKUP(_xlfn.XLOOKUP(A45,Orders_Raw!A:A,Orders_Raw!B:B),Customers_Raw!A:A,Customers_Raw!E:E) -> Corporate | N45: =IF(COUNTIF($A$2:A45,A45)=1,1,0) -> 1
A46: O50165 | B46: P1014 | C46: 4 | D46: 68764.7 | E46: =_xlfn.XLOOKUP(Order_Items_Raw!B614,Products_Raw!A:A,Products_Raw!D:D) -> 2144.79 | F46: =D46-(C46*E46) -> 60185.54 | G46: =PROPER(TRIM(CLEAN(_xlfn.XLOOKUP(Order_Items_Raw!A614,Orders_Raw!A:A,Orders_Raw!E:E)))) -> Website | H46: =_xlfn.XLOOKUP(B46,Products_Raw!A:A,Products_Raw!C:C) -> Fashion | I46: =_xlfn.XLOOKUP(_xlfn.XLOOKUP(A46,Orders_Raw!A:A,Orders_Raw!B:B),Customers_Raw!A:A,Customers_Raw!E:E) -> Consumer | J46: =_xlfn.XLOOKUP(Order_Items_Raw!A614,Orders_Raw!A:A,Orders_Raw!C:C) -> 45899 | K46: Aug | L46: =_xlfn.XLOOKUP(A46,Orders_Raw!A:A,Orders_Raw!D:D) -> Delivered | M46: =_xlfn.XLOOKUP(_xlfn.XLOOKUP(A46,Orders_Raw!A:A,Orders_Raw!B:B),Customers_Raw!A:A,Customers_Raw!E:E) -> Consumer | N46: =IF(COUNTIF($A$2:A46,A46)=1,1,0) -> 0
A47: O50835 | B47: P1014 | C47: 3 | D47: 40424.35 | E47: =_xlfn.XLOOKUP(Order_Items_Raw!B625,Products_Raw!A:A,Products_Raw!D:D) -> 4370.8 | F47: =D47-(C47*E47) -> 27311.95 | G47: =PROPER(TRIM(CLEAN(_xlfn.XLOOKUP(Order_Items_Raw!A625,Orders_Raw!A:A,Orders_Raw!E:E)))) -> Website | H47: =_xlfn.XLOOKUP(B47,Products_Raw!A:A,Products_Raw!C:C) -> Fashion | I47: =_xlfn.XLOOKUP(_xlfn.XLOOKUP(A47,Orders_Raw!A:A,Orders_Raw!B:B),Customers_Raw!A:A,Customers_Raw!E:E) -> Consumer | J47: =_xlfn.XLOOKUP(Order_Items_Raw!A625,Orders_Raw!A:A,Orders_Raw!C:C) -> 45874 | K47: Aug | L47: =_xlfn.XLOOKUP(A47,Orders_Raw!A:A,Orders_Raw!D:D) -> Delivered | M47: =_xlfn.XLOOKUP(_xlfn.XLOOKUP(A47,Orders_Raw!A:A,Orders_Raw!B:B),Customers_Raw!A:A,Customers_Raw!E:E) -> Consumer | N47: =IF(COUNTIF($A$2:A47,A47)=1,1,0) -> 1
A48: O52385 | B48: P1014 | C48: 1 | D48: 15327.58 | E48: =_xlfn.XLOOKUP(Order_Items_Raw!B653,Products_Raw!A:A,Products_Raw!D:D) -> 4936.19 | F48: =D48-(C48*E48) -> 10391.39 | G48: =PROPER(TRIM(CLEAN(_xlfn.XLOOKUP(Order_Items_Raw!A653,Orders_Raw!A:A,Orders_Raw!E:E)))) -> Website | H48: =_xlfn.XLOOKUP(B48,Products_Raw!A:A,Products_Raw!C:C) -> Fashion | I48: =_xlfn.XLOOKUP(_xlfn.XLOOKUP(A48,Orders_Raw!A:A,Orders_Raw!B:B),Customers_Raw!A:A,Customers_Raw!E:E) -> Consumer | J48: =_xlfn.XLOOKUP(Order_Items_Raw!A653,Orders_Raw!A:A,Orders_Raw!C:C) -> 46016 | K48: Dec | L48: =_xlfn.XLOOKUP(A48,Orders_Raw!A:A,Orders_Raw!D:D) -> Delivered | M48: =_xlfn.XLOOKUP(_xlfn.XLOOKUP(A48,Orders_Raw!A:A,Orders_Raw!B:B),Customers_Raw!A:A,Customers_Raw!E:E) -> Consumer | N48: =IF(COUNTIF($A$2:A48,A48)=1,1,0) -> 1
A49: O50476 | B49: P1015 | C49: 4 | D49: 1609.92 | E49: =_xlfn.XLOOKUP(Order_Items_Raw!B663,Products_Raw!A:A,Products_Raw!D:D) -> 6579.03 | F49: =D49-(C49*E49) -> -24706.2 | G49: =PROPER(TRIM(CLEAN(_xlfn.XLOOKUP(Order_Items_Raw!A663,Orders_Raw!A:A,Orders_Raw!E:E)))) -> Website | H49: =_xlfn.XLOOKUP(B49,Products_Raw!A:A,Products_Raw!C:C) -> Fashion | I49: =_xlfn.XLOOKUP(_xlfn.XLOOKUP(A49,Orders_Raw!A:A,Orders_Raw!B:B),Customers_Raw!A:A,Customers_Raw!E:E) -> Corporate | J49: =_xlfn.XLOOKUP(Order_Items_Raw!A663,Orders_Raw!A:A,Orders_Raw!C:C) -> 45995 | K49: Dec | L49: =_xlfn.XLOOKUP(A49,Orders_Raw!A:A,Orders_Raw!D:D) -> Delivered | M49: =_xlfn.XLOOKUP(_xlfn.XLOOKUP(A49,Orders_Raw!A:A,Orders_Raw!B:B),Customers_Raw!A:A,Customers_Raw!E:E) -> Corporate | N49: =IF(COUNTIF($A$2:A49,A49)=1,1,0) -> 1
A50: O50996 | B50: P1015 | C50: 1 | D50: 474.71 | E50: =_xlfn.XLOOKUP(Order_Items_Raw!B673,Products_Raw!A:A,Products_Raw!D:D) -> 7144.88 | F50: =D50-(C50*E50) -> -6670.17 | G50: =PROPER(TRIM(CLEAN(_xlfn.XLOOKUP(Order_Items_Raw!A673,Orders_Raw!A:A,Orders_Raw!E:E)))) -> Website | H50: =_xlfn.XLOOKUP(B50,Products_Raw!A:A,Products_Raw!C:C) -> Fashion | I50: =_xlfn.XLOOKUP(_xlfn.XLOOKUP(A50,Orders_Raw!A:A,Orders_Raw!B:B),Customers_Raw!A:A,Customers_Raw!E:E) -> Corporate | J50: =_xlfn.XLOOKUP(Order_Items_Raw!A673,Orders_Raw!A:A,Orders_Raw!C:C) -> 46007 | K50: Dec | L50: =_xlfn.XLOOKUP(A50,Orders_Raw!A:A,Orders_Raw!D:D) -> Cancelled | M50: =_xlfn.XLOOKUP(_xlfn.XLOOKUP(A50,Orders_Raw!A:A,Orders_Raw!B:B),Customers_Raw!A:A,Customers_Raw!E:E) -> Corporate | N50: =IF(COUNTIF($A$2:A50,A50)=1,1,0) -> 1
A51: O51134 | B51: P1015 | C51: 4 | D51: 1791.81 | E51: =_xlfn.XLOOKUP(Order_Items_Raw!B678,Products_Raw!A:A,Products_Raw!D:D) -> 7144.88 | F51: =D51-(C51*E51) -> -26787.71 | G51: =PROPER(TRIM(CLEAN(_xlfn.XLOOKUP(Order_Items_Raw!A678,Orders_Raw!A:A,Orders_Raw!E:E)))) -> Website | H51: =_xlfn.XLOOKUP(B51,Products_Raw!A:A,Products_Raw!C:C) -> Fashion | I51: =_xlfn.XLOOKUP(_xlfn.XLOOKUP(A51,Orders_Raw!A:A,Orders_Raw!B:B),Customers_Raw!A:A,Customers_Raw!E:E) -> Consumer | J51: =_xlfn.XLOOKUP(Order_Items_Raw!A678,Orders_Raw!A:A,Orders_Raw!C:C) -> 45993 | K51: Dec | L51: =_xlfn.XLOOKUP(A51,Orders_Raw!A:A,Orders_Raw!D:D) -> Delivered | M51: =_xlfn.XLOOKUP(_xlfn.XLOOKUP(A51,Orders_Raw!A:A,Orders_Raw!B:B),Customers_Raw!A:A,Customers_Raw!E:E) -> Consumer | N51: =IF(COUNTIF($A$2:A51,A51)=1,1,0) -> 1
A52: O51673 | B52: P1015 | C52: 2 | D52: 738.96 | E52: =_xlfn.XLOOKUP(Order_Items_Raw!B685,Products_Raw!A:A,Products_Raw!D:D) -> 4703.24 | F52: =D52-(C52*E52) -> -8667.52 | G52: =PROPER(TRIM(CLEAN(_xlfn.XLOOKUP(Order_Items_Raw!A685,Orders_Raw!A:A,Orders_Raw!E:E)))) -> Website | H52: =_xlfn.XLOOKUP(B52,Products_Raw!A:A,Products_Raw!C:C) -> Fashion | I52: =_xlfn.XLOOKUP(_xlfn.XLOOKUP(A52,Orders_Raw!A:A,Orders_Raw!B:B),Customers_Raw!A:A,Customers_Raw!E:E) -> Consumer | J52: =_xlfn.XLOOKUP(Order_Items_Raw!A685,Orders_Raw!A:A,Orders_Raw!C:C) -> 45994 | K52: Dec | L52: =_xlfn.XLOOKUP(A52,Orders_Raw!A:A,Orders_Raw!D:D) -> Delivered | M52: =_xlfn.XLOOKUP(_xlfn.XLOOKUP(A52,Orders_Raw!A:A,Orders_Raw!B:B),Customers_Raw!A:A,Customers_Raw!E:E) -> Consumer | N52: =IF(COUNTIF($A$2:A52,A52)=1,1,0) -> 1
A53: O51863 | B53: P1015 | C53: 1 | D53: 451.91 | E53: =_xlfn.XLOOKUP(Order_Items_Raw!B693,Products_Raw!A:A,Products_Raw!D:D) -> 9148.31 | F53: =D53-(C53*E53) -> -8696.4 | G53: =PROPER(TRIM(CLEAN(_xlfn.XLOOKUP(Order_Items_Raw!A693,Orders_Raw!A:A,Orders_Raw!E:E)))) -> Mobile App | H53: =_xlfn.XLOOKUP(B53,Products_Raw!A:A,Products_Raw!C:C) -> Fashion | I53: =_xlfn.XLOOKUP(_xlfn.XLOOKUP(A53,Orders_Raw!A:A,Orders_Raw!B:B),Customers_Raw!A:A,Customers_Raw!E:E) -> Small Business | J53: =_xlfn.XLOOKUP(Order_Items_Raw!A693,Orders_Raw!A:A,Orders_Raw!C:C) -> 46009 | K53: Dec | L53: =_xlfn.XLOOKUP(A53,Orders_Raw!A:A,Orders_Raw!D:D) -> Delivered | M53: =_xlfn.XLOOKUP(_xlfn.XLOOKUP(A53,Orders_Raw!A:A,Orders_Raw!B:B),Customers_Raw!A:A,Customers_Raw!E:E) -> Small Business | N53: =IF(COUNTIF($A$2:A53,A53)=1,1,0) -> 1
A54: O51899 | B54: P1015 | C54: 3 | D54: 1406.28 | E54: =_xlfn.XLOOKUP(Order_Items_Raw!B696,Products_Raw!A:A,Products_Raw!D:D) -> 9148.31 | F54: =D54-(C54*E54) -> -26038.65 | G54: =PROPER(TRIM(CLEAN(_xlfn.XLOOKUP(Order_Items_Raw!A696,Orders_Raw!A:A,Orders_Raw!E:E)))) -> Mobile App | H54: =_xlfn.XLOOKUP(B54,Products_Raw!A:A,Products_Raw!C:C) -> Fashion | I54: =_xlfn.XLOOKUP(_xlfn.XLOOKUP(A54,Orders_Raw!A:A,Orders_Raw!B:B),Customers_Raw!A:A,Customers_Raw!E:E) -> Corporate | J54: =_xlfn.XLOOKUP(Order_Items_Raw!A696,Orders_Raw!A:A,Orders_Raw!C:C) -> 46010 | K54: Dec | L54: =_xlfn.XLOOKUP(A54,Orders_Raw!A:A,Orders_Raw!D:D) -> Delivered | M54: =_xlfn.XLOOKUP(_xlfn.XLOOKUP(A54,Orders_Raw!A:A,Orders_Raw!B:B),Customers_Raw!A:A,Customers_Raw!E:E) -> Corporate | N54: =IF(COUNTIF($A$2:A54,A54)=1,1,0) -> 1
A55: O51994 | B55: P1015 | C55: 3 | D55: 1435.84 | E55: =_xlfn.XLOOKUP(Order_Items_Raw!B698,Products_Raw!A:A,Products_Raw!D:D) -> 9148.31 | F55: =D55-(C55*E55) -> -26009.09 | G55: =PROPER(TRIM(CLEAN(_xlfn.XLOOKUP(Order_Items_Raw!A698,Orders_Raw!A:A,Orders_Raw!E:E)))) -> Website | H55: =_xlfn.XLOOKUP(B55,Products_Raw!A:A,Products_Raw!C:C) -> Fashion | I55: =_xlfn.XLOOKUP(_xlfn.XLOOKUP(A55,Orders_Raw!A:A,Orders_Raw!B:B),Customers_Raw!A:A,Customers_Raw!E:E) -> Consumer | J55: =_xlfn.XLOOKUP(Order_Items_Raw!A698,Orders_Raw!A:A,Orders_Raw!C:C) -> 45993 | K55: Dec | L55: =_xlfn.XLOOKUP(A55,Orders_Raw!A:A,Orders_Raw!D:D) -> Delivered | M55: =_xlfn.XLOOKUP(_xlfn.XLOOKUP(A55,Orders_Raw!A:A,Orders_Raw!B:B),Customers_Raw!A:A,Customers_Raw!E:E) -> Consumer | N55: =IF(COUNTIF($A$2:A55,A55)=1,1,0) -> 1
A56: O52295 | B56: P1015 | C56: 4 | D56: 1529.82 | E56: =_xlfn.XLOOKUP(Order_Items_Raw!B707,Products_Raw!A:A,Products_Raw!D:D) -> 295.87 | F56: =D56-(C56*E56) -> 346.34 | G56: =PROPER(TRIM(CLEAN(_xlfn.XLOOKUP(Order_Items_Raw!A707,Orders_Raw!A:A,Orders_Raw!E:E)))) -> Mobile App | H56: =_xlfn.XLOOKUP(B56,Products_Raw!A:A,Products_Raw!C:C) -> Fashion | I56: =_xlfn.XLOOKUP(_xlfn.XLOOKUP(A56,Orders_Raw!A:A,Orders_Raw!B:B),Customers_Raw!A:A,Customers_Raw!E:E) -> Consumer | J56: =_xlfn.XLOOKUP(Order_Items_Raw!A707,Orders_Raw!A:A,Orders_Raw!C:C) -> 46009 | K56: Dec | L56: =_xlfn.XLOOKUP(A56,Orders_Raw!A:A,Orders_Raw!D:D) -> Delivered | M56: =_xlfn.XLOOKUP(_xlfn.XLOOKUP(A56,Orders_Raw!A:A,Orders_Raw!B:B),Customers_Raw!A:A,Customers_Raw!E:E) -> Consumer | N56: =IF(COUNTIF($A$2:A56,A56)=1,1,0) -> 1
A57: O52305 | B57: P1016 | C57: 4 | D57: 22619.49 | E57: =_xlfn.XLOOKUP(Order_Items_Raw!B752,Products_Raw!A:A,Products_Raw!D:D) -> 4176.26 | F57: =D57-(C57*E57) -> 5914.45 | G57: =PROPER(TRIM(CLEAN(_xlfn.XLOOKUP(Order_Items_Raw!A752,Orders_Raw!A:A,Orders_Raw!E:E)))) -> Website | H57: =_xlfn.XLOOKUP(B57,Products_Raw!A:A,Products_Raw!C:C) -> Sports | I57: =_xlfn.XLOOKUP(_xlfn.XLOOKUP(A57,Orders_Raw!A:A,Orders_Raw!B:B),Customers_Raw!A:A,Customers_Raw!E:E) -> Consumer | J57: =_xlfn.XLOOKUP(Order_Items_Raw!A752,Orders_Raw!A:A,Orders_Raw!C:C) -> 46019 | K57: Dec | L57: =_xlfn.XLOOKUP(A57,Orders_Raw!A:A,Orders_Raw!D:D) -> Delivered | M57: =_xlfn.XLOOKUP(_xlfn.XLOOKUP(A57,Orders_Raw!A:A,Orders_Raw!B:B),Customers_Raw!A:A,Customers_Raw!E:E) -> Consumer | N57: =IF(COUNTIF($A$2:A57,A57)=1,1,0) -> 1
A58: O52329 | B58: P1016 | C58: 1 | D58: 6162.74 | E58: =_xlfn.XLOOKUP(Order_Items_Raw!B753,Products_Raw!A:A,Products_Raw!D:D) -> 4176.26 | F58: =D58-(C58*E58) -> 1986.48 | G58: =PROPER(TRIM(CLEAN(_xlfn.XLOOKUP(Order_Items_Raw!A753,Orders_Raw!A:A,Orders_Raw!E:E)))) -> Mobile App | H58: =_xlfn.XLOOKUP(B58,Products_Raw!A:A,Products_Raw!C:C) -> Sports | I58: =_xlfn.XLOOKUP(_xlfn.XLOOKUP(A58,Orders_Raw!A:A,Orders_Raw!B:B),Customers_Raw!A:A,Customers_Raw!E:E) -> Corporate | J58: =_xlfn.XLOOKUP(Order_Items_Raw!A753,Orders_Raw!A:A,Orders_Raw!C:C) -> 46013 | K58: Dec | L58: =_xlfn.XLOOKUP(A58,Orders_Raw!A:A,Orders_Raw!D:D) -> Delivered | M58: =_xlfn.XLOOKUP(_xlfn.XLOOKUP(A58,Orders_Raw!A:A,Orders_Raw!B:B),Customers_Raw!A:A,Customers_Raw!E:E) -> Corporate | N58: =IF(COUNTIF($A$2:A58,A58)=1,1,0) -> 1
A59: O52385 | B59: P1016 | C59: 3 | D59: 18585.43 | E59: =_xlfn.XLOOKUP(Order_Items_Raw!B755,Products_Raw!A:A,Products_Raw!D:D) -> 4176.26 | F59: =D59-(C59*E59) -> 6056.65 | G59: =PROPER(TRIM(CLEAN(_xlfn.XLOOKUP(Order_Items_Raw!A755,Orders_Raw!A:A,Orders_Raw!E:E)))) -> Website | H59: =_xlfn.XLOOKUP(B59,Products_Raw!A:A,Products_Raw!C:C) -> Sports | I59: =_xlfn.XLOOKUP(_xlfn.XLOOKUP(A59,Orders_Raw!A:A,Orders_Raw!B:B),Customers_Raw!A:A,Customers_Raw!E:E) -> Consumer | J59: =_xlfn.XLOOKUP(Order_Items_Raw!A755,Orders_Raw!A:A,Orders_Raw!C:C) -> 46000 | K59: Dec | L59: =_xlfn.XLOOKUP(A59,Orders_Raw!A:A,Orders_Raw!D:D) -> Delivered | M59: =_xlfn.XLOOKUP(_xlfn.XLOOKUP(A59,Orders_Raw!A:A,Orders_Raw!B:B),Customers_Raw!A:A,Customers_Raw!E:E) -> Consumer | N59: =IF(COUNTIF($A$2:A59,A59)=1,1,0) -> 0
A60: O50198 | B60: P1017 | C60: 4 | D60: 2515.69 | E60: =_xlfn.XLOOKUP(Order_Items_Raw!B761,Products_Raw!A:A,Products_Raw!D:D) -> 6279.29 | F60: =D60-(C60*E60) -> -22601.47 | G60: =PROPER(TRIM(CLEAN(_xlfn.XLOOKUP(Order_Items_Raw!A761,Orders_Raw!A:A,Orders_Raw!E:E)))) -> Website | H60: =_xlfn.XLOOKUP(B60,Products_Raw!A:A,Products_Raw!C:C) -> Electronics | I60: =_xlfn.XLOOKUP(_xlfn.XLOOKUP(A60,Orders_Raw!A:A,Orders_Raw!B:B),Customers_Raw!A:A,Customers_Raw!E:E) -> Corporate | J60: =_xlfn.XLOOKUP(Order_Items_Raw!A761,Orders_Raw!A:A,Orders_Raw!C:C) -> 46022 | K60: Dec | L60: =_xlfn.XLOOKUP(A60,Orders_Raw!A:A,Orders_Raw!D:D) -> Cancelled | M60: =_xlfn.XLOOKUP(_xlfn.XLOOKUP(A60,Orders_Raw!A:A,Orders_Raw!B:B),Customers_Raw!A:A,Customers_Raw!E:E) -> Corporate | N60: =IF(COUNTIF($A$2:A60,A60)=1,1,0) -> 1
A61: O50450 | B61: P1017 | C61: 2 | D61: 1459.58 | E61: =_xlfn.XLOOKUP(Order_Items_Raw!B764,Products_Raw!A:A,Products_Raw!D:D) -> 229.52 | F61: =D61-(C61*E61) -> 1000.54 | G61: =PROPER(TRIM(CLEAN(_xlfn.XLOOKUP(Order_Items_Raw!A764,Orders_Raw!A:A,Orders_Raw!E:E)))) -> Website | H61: =_xlfn.XLOOKUP(B61,Products_Raw!A:A,Products_Raw!C:C) -> Electronics | I61: =_xlfn.XLOOKUP(_xlfn.XLOOKUP(A61,Orders_Raw!A:A,Orders_Raw!B:B),Customers_Raw!A:A,Customers_Raw!E:E) -> Consumer | J61: =_xlfn.XLOOKUP(Order_Items_Raw!A764,Orders_Raw!A:A,Orders_Raw!C:C) -> 46009 | K61: Dec | L61: =_xlfn.XLOOKUP(A61,Orders_Raw!A:A,Orders_Raw!D:D) -> Delivered | M61: =_xlfn.XLOOKUP(_xlfn.XLOOKUP(A61,Orders_Raw!A:A,Orders_Raw!B:B),Customers_Raw!A:A,Customers_Raw!E:E) -> Consumer | N61: =IF(COUNTIF($A$2:A61,A61)=1,1,0) -> 1
A62: O50821 | B62: P1017 | C62: 1 | D62: 556.45 | E62: =_xlfn.XLOOKUP(Order_Items_Raw!B774,Products_Raw!A:A,Products_Raw!D:D) -> 9531.89 | F62: =D62-(C62*E62) -> -8975.44 | G62: =PROPER(TRIM(CLEAN(_xlfn.XLOOKUP(Order_Items_Raw!A774,Orders_Raw!A:A,Orders_Raw!E:E)))) -> Website | H62: =_xlfn.XLOOKUP(B62,Products_Raw!A:A,Products_Raw!C:C) -> Electronics | I62: =_xlfn.XLOOKUP(_xlfn.XLOOKUP(A62,Orders_Raw!A:A,Orders_Raw!B:B),Customers_Raw!A:A,Customers_Raw!E:E) -> Consumer | J62: =_xlfn.XLOOKUP(Order_Items_Raw!A774,Orders_Raw!A:A,Orders_Raw!C:C) -> 45993 | K62: Dec | L62: =_xlfn.XLOOKUP(A62,Orders_Raw!A:A,Orders_Raw!D:D) -> Delivered | M62: =_xlfn.XLOOKUP(_xlfn.XLOOKUP(A62,Orders_Raw!A:A,Orders_Raw!B:B),Customers_Raw!A:A,Customers_Raw!E:E) -> Consumer | N62: =IF(COUNTIF($A$2:A62,A62)=1,1,0) -> 1
A63: O51578 | B63: P1017 | C63: 2 | D63: 1448.77 | E63: =_xlfn.XLOOKUP(Order_Items_Raw!B791,Products_Raw!A:A,Products_Raw!D:D) -> 6443.36 | F63: =D63-(C63*E63) -> -11437.95 | G63: =PROPER(TRIM(CLEAN(_xlfn.XLOOKUP(Order_Items_Raw!A791,Orders_Raw!A:A,Orders_Raw!E:E)))) -> Website | H63: =_xlfn.XLOOKUP(B63,Products_Raw!A:A,Products_Raw!C:C) -> Electronics | I63: =_xlfn.XLOOKUP(_xlfn.XLOOKUP(A63,Orders_Raw!A:A,Orders_Raw!B:B),Customers_Raw!A:A,Customers_Raw!E:E) -> Consumer | J63: =_xlfn.XLOOKUP(Order_Items_Raw!A791,Orders_Raw!A:A,Orders_Raw!C:C) -> 45995 | K63: Dec | L63: =_xlfn.XLOOKUP(A63,Orders_Raw!A:A,Orders_Raw!D:D) -> Delivered | M63: =_xlfn.XLOOKUP(_xlfn.XLOOKUP(A63,Orders_Raw!A:A,Orders_Raw!B:B),Customers_Raw!A:A,Customers_Raw!E:E) -> Consumer | N63: =IF(COUNTIF($A$2:A63,A63)=1,1,0) -> 1
A64: O50091 | B64: P1018 | C64: 2 | D64: 11123.71 | E64: =_xlfn.XLOOKUP(Order_Items_Raw!B806,Products_Raw!A:A,Products_Raw!D:D) -> 2133.21 | F64: =D64-(C64*E64) -> 6857.29 | G64: =PROPER(TRIM(CLEAN(_xlfn.XLOOKUP(Order_Items_Raw!A806,Orders_Raw!A:A,Orders_Raw!E:E)))) -> Mobile App | H64: =_xlfn.XLOOKUP(B64,Products_Raw!A:A,Products_Raw!C:C) -> Beauty | I64: =_xlfn.XLOOKUP(_xlfn.XLOOKUP(A64,Orders_Raw!A:A,Orders_Raw!B:B),Customers_Raw!A:A,Customers_Raw!E:E) -> Small Business | J64: =_xlfn.XLOOKUP(Order_Items_Raw!A806,Orders_Raw!A:A,Orders_Raw!C:C) -> 46006 | K64: Dec | L64: =_xlfn.XLOOKUP(A64,Orders_Raw!A:A,Orders_Raw!D:D) -> Delivered | M64: =_xlfn.XLOOKUP(_xlfn.XLOOKUP(A64,Orders_Raw!A:A,Orders_Raw!B:B),Customers_Raw!A:A,Customers_Raw!E:E) -> Small Business | N64: =IF(COUNTIF($A$2:A64,A64)=1,1,0) -> 1
A65: O50424 | B65: P1018 | C65: 3 | D65: 21783.9 | E65: =_xlfn.XLOOKUP(Order_Items_Raw!B815,Products_Raw!A:A,Products_Raw!D:D) -> 2857.57 | F65: =D65-(C65*E65) -> 13211.19 | G65: =PROPER(TRIM(CLEAN(_xlfn.XLOOKUP(Order_Items_Raw!A815,Orders_Raw!A:A,Orders_Raw!E:E)))) -> Marketplace | H65: =_xlfn.XLOOKUP(B65,Products_Raw!A:A,Products_Raw!C:C) -> Beauty | I65: =_xlfn.XLOOKUP(_xlfn.XLOOKUP(A65,Orders_Raw!A:A,Orders_Raw!B:B),Customers_Raw!A:A,Customers_Raw!E:E) -> Consumer | J65: =_xlfn.XLOOKUP(Order_Items_Raw!A815,Orders_Raw!A:A,Orders_Raw!C:C) -> 46004 | K65: Dec | L65: =_xlfn.XLOOKUP(A65,Orders_Raw!A:A,Orders_Raw!D:D) -> Delivered | M65: =_xlfn.XLOOKUP(_xlfn.XLOOKUP(A65,Orders_Raw!A:A,Orders_Raw!B:B),Customers_Raw!A:A,Customers_Raw!E:E) -> Consumer | N65: =IF(COUNTIF($A$2:A65,A65)=1,1,0) -> 1
A66: O50853 | B66: P1018 | C66: 2 | D66: 12012.39 | E66: =_xlfn.XLOOKUP(Order_Items_Raw!B820,Products_Raw!A:A,Products_Raw!D:D) -> 11732.81 | F66: =D66-(C66*E66) -> -11453.23 | G66: =PROPER(TRIM(CLEAN(_xlfn.XLOOKUP(Order_Items_Raw!A820,Orders_Raw!A:A,Orders_Raw!E:E)))) -> Mobile App | H66: =_xlfn.XLOOKUP(B66,Products_Raw!A:A,Products_Raw!C:C) -> Beauty | I66: =_xlfn.XLOOKUP(_xlfn.XLOOKUP(A66,Orders_Raw!A:A,Orders_Raw!B:B),Customers_Raw!A:A,Customers_Raw!E:E) -> Corporate | J66: =_xlfn.XLOOKUP(Order_Items_Raw!A820,Orders_Raw!A:A,Orders_Raw!C:C) -> 45993 | K66: Dec | L66: =_xlfn.XLOOKUP(A66,Orders_Raw!A:A,Orders_Raw!D:D) -> Delivered | M66: =_xlfn.XLOOKUP(_xlfn.XLOOKUP(A66,Orders_Raw!A:A,Orders_Raw!B:B),Customers_Raw!A:A,Customers_Raw!E:E) -> Corporate | N66: =IF(COUNTIF($A$2:A66,A66)=1,1,0) -> 1
A67: O50858 | B67: P1018 | C67: 4 | D67: 26558.54 | E67: =_xlfn.XLOOKUP(Order_Items_Raw!B821,Products_Raw!A:A,Products_Raw!D:D) -> 11732.81 | F67: =D67-(C67*E67) -> -20372.7 | G67: =PROPER(TRIM(CLEAN(_xlfn.XLOOKUP(Order_Items_Raw!A821,Orders_Raw!A:A,Orders_Raw!E:E)))) -> Marketplace | H67: =_xlfn.XLOOKUP(B67,Products_Raw!A:A,Products_Raw!C:C) -> Beauty | I67: =_xlfn.XLOOKUP(_xlfn.XLOOKUP(A67,Orders_Raw!A:A,Orders_Raw!B:B),Customers_Raw!A:A,Customers_Raw!E:E) -> Consumer | J67: =_xlfn.XLOOKUP(Order_Items_Raw!A821,Orders_Raw!A:A,Orders_Raw!C:C) -> 45992 | K67: Dec | L67: =_xlfn.XLOOKUP(A67,Orders_Raw!A:A,Orders_Raw!D:D) -> Delivered | M67: =_xlfn.XLOOKUP(_xlfn.XLOOKUP(A67,Orders_Raw!A:A,Orders_Raw!B:B),Customers_Raw!A:A,Customers_Raw!E:E) -> Consumer | N67: =IF(COUNTIF($A$2:A67,A67)=1,1,0) -> 1
A68: O51573 | B68: P1018 | C68: 1 | D68: 6716.91 | E68: =_xlfn.XLOOKUP(Order_Items_Raw!B839,Products_Raw!A:A,Products_Raw!D:D) -> 11118.8 | F68: =D68-(C68*E68) -> -4401.89 | G68: =PROPER(TRIM(CLEAN(_xlfn.XLOOKUP(Order_Items_Raw!A839,Orders_Raw!A:A,Orders_Raw!E:E)))) -> Marketplace | H68: =_xlfn.XLOOKUP(B68,Products_Raw!A:A,Products_Raw!C:C) -> Beauty | I68: =_xlfn.XLOOKUP(_xlfn.XLOOKUP(A68,Orders_Raw!A:A,Orders_Raw!B:B),Customers_Raw!A:A,Customers_Raw!E:E) -> Small Business | J68: =_xlfn.XLOOKUP(Order_Items_Raw!A839,Orders_Raw!A:A,Orders_Raw!C:C) -> 46011 | K68: Dec | L68: =_xlfn.XLOOKUP(A68,Orders_Raw!A:A,Orders_Raw!D:D) -> Delivered | M68: =_xlfn.XLOOKUP(_xlfn.XLOOKUP(A68,Orders_Raw!A:A,Orders_Raw!B:B),Customers_Raw!A:A,Customers_Raw!E:E) -> Small Business | N68: =IF(COUNTIF($A$2:A68,A68)=1,1,0) -> 1
A69: O51722 | B69: P1018 | C69: 3 | D69: 21770.57 | E69: =_xlfn.XLOOKUP(Order_Items_Raw!B842,Products_Raw!A:A,Products_Raw!D:D) -> 11118.8 | F69: =D69-(C69*E69) -> -11585.83 | G69: =PROPER(TRIM(CLEAN(_xlfn.XLOOKUP(Order_Items_Raw!A842,Orders_Raw!A:A,Orders_Raw!E:E)))) -> Mobile App | H69: =_xlfn.XLOOKUP(B69,Products_Raw!A:A,Products_Raw!C:C) -> Beauty | I69: =_xlfn.XLOOKUP(_xlfn.XLOOKUP(A69,Orders_Raw!A:A,Orders_Raw!B:B),Customers_Raw!A:A,Customers_Raw!E:E) -> Corporate | J69: =_xlfn.XLOOKUP(Order_Items_Raw!A842,Orders_Raw!A:A,Orders_Raw!C:C) -> 46019 | K69: Dec | L69: =_xlfn.XLOOKUP(A69,Orders_Raw!A:A,Orders_Raw!D:D) -> Delivered | M69: =_xlfn.XLOOKUP(_xlfn.XLOOKUP(A69,Orders_Raw!A:A,Orders_Raw!B:B),Customers_Raw!A:A,Customers_Raw!E:E) -> Corporate | N69: =IF(COUNTIF($A$2:A69,A69)=1,1,0) -> 1
A70: O51914 | B70: P1019 | C70: 3 | D70: 28484.29 | E70: =_xlfn.XLOOKUP(Order_Items_Raw!B890,Products_Raw!A:A,Products_Raw!D:D) -> 516.61 | F70: =D70-(C70*E70) -> 26934.46 | G70: =PROPER(TRIM(CLEAN(_xlfn.XLOOKUP(Order_Items_Raw!A890,Orders_Raw!A:A,Orders_Raw!E:E)))) -> Website | H70: =_xlfn.XLOOKUP(B70,Products_Raw!A:A,Products_Raw!C:C) -> Home & Kitchen | I70: =_xlfn.XLOOKUP(_xlfn.XLOOKUP(A70,Orders_Raw!A:A,Orders_Raw!B:B),Customers_Raw!A:A,Customers_Raw!E:E) -> Consumer | J70: =_xlfn.XLOOKUP(Order_Items_Raw!A890,Orders_Raw!A:A,Orders_Raw!C:C) -> 46008 | K70: Dec | L70: =_xlfn.XLOOKUP(A70,Orders_Raw!A:A,Orders_Raw!D:D) -> Delivered | M70: =_xlfn.XLOOKUP(_xlfn.XLOOKUP(A70,Orders_Raw!A:A,Orders_Raw!B:B),Customers_Raw!A:A,Customers_Raw!E:E) -> Consumer | N70: =IF(COUNTIF($A$2:A70,A70)=1,1,0) -> 1
A71: O52107 | B71: P1019 | C71: 2 | D71: 16347 | E71: =_xlfn.XLOOKUP(Order_Items_Raw!B893,Products_Raw!A:A,Products_Raw!D:D) -> 11653.29 | F71: =D71-(C71*E71) -> -6959.58 | G71: =PROPER(TRIM(CLEAN(_xlfn.XLOOKUP(Order_Items_Raw!A893,Orders_Raw!A:A,Orders_Raw!E:E)))) -> Mobile App | H71: =_xlfn.XLOOKUP(B71,Products_Raw!A:A,Products_Raw!C:C) -> Home & Kitchen | I71: =_xlfn.XLOOKUP(_xlfn.XLOOKUP(A71,Orders_Raw!A:A,Orders_Raw!B:B),Customers_Raw!A:A,Customers_Raw!E:E) -> Consumer | J71: =_xlfn.XLOOKUP(Order_Items_Raw!A893,Orders_Raw!A:A,Orders_Raw!C:C) -> 46014 | K71: Dec | L71: =_xlfn.XLOOKUP(A71,Orders_Raw!A:A,Orders_Raw!D:D) -> Delivered | M71: =_xlfn.XLOOKUP(_xlfn.XLOOKUP(A71,Orders_Raw!A:A,Orders_Raw!B:B),Customers_Raw!A:A,Customers_Raw!E:E) -> Consumer | N71: =IF(COUNTIF($A$2:A71,A71)=1,1,0) -> 1
A72: O50005 | B72: P1020 | C72: 1 | D72: 8603.24 | E72: =_xlfn.XLOOKUP(Order_Items_Raw!B902,Products_Raw!A:A,Products_Raw!D:D) -> 11764.29 | F72: =D72-(C72*E72) -> -3161.05 | G72: =PROPER(TRIM(CLEAN(_xlfn.XLOOKUP(Order_Items_Raw!A902,Orders_Raw!A:A,Orders_Raw!E:E)))) -> Website | H72: =_xlfn.XLOOKUP(B72,Products_Raw!A:A,Products_Raw!C:C) -> Home & Kitchen | I72: =_xlfn.XLOOKUP(_xlfn.XLOOKUP(A72,Orders_Raw!A:A,Orders_Raw!B:B),Customers_Raw!A:A,Customers_Raw!E:E) -> Corporate | J72: =_xlfn.XLOOKUP(Order_Items_Raw!A902,Orders_Raw!A:A,Orders_Raw!C:C) -> 46009 | K72: Dec | L72: =_xlfn.XLOOKUP(A72,Orders_Raw!A:A,Orders_Raw!D:D) -> Delivered | M72: =_xlfn.XLOOKUP(_xlfn.XLOOKUP(A72,Orders_Raw!A:A,Orders_Raw!B:B),Customers_Raw!A:A,Customers_Raw!E:E) -> Corporate | N72: =IF(COUNTIF($A$2:A72,A72)=1,1,0) -> 1
A73: O50302 | B73: P1020 | C73: 1 | D73: 7438.59 | E73: =_xlfn.XLOOKUP(Order_Items_Raw!B906,Products_Raw!A:A,Products_Raw!D:D) -> 11764.29 | F73: =D73-(C73*E73) -> -4325.7 | G73: =PROPER(TRIM(CLEAN(_xlfn.XLOOKUP(Order_Items_Raw!A906,Orders_Raw!A:A,Orders_Raw!E:E)))) -> Mobile App | H73: =_xlfn.XLOOKUP(B73,Products_Raw!A:A,Products_Raw!C:C) -> Home & Kitchen | I73: =_xlfn.XLOOKUP(_xlfn.XLOOKUP(A73,Orders_Raw!A:A,Orders_Raw!B:B),Customers_Raw!A:A,Customers_Raw!E:E) -> Corporate | J73: =_xlfn.XLOOKUP(Order_Items_Raw!A906,Orders_Raw!A:A,Orders_Raw!C:C) -> 46003 | K73: Dec | L73: =_xlfn.XLOOKUP(A73,Orders_Raw!A:A,Orders_Raw!D:D) -> Delivered | M73: =_xlfn.XLOOKUP(_xlfn.XLOOKUP(A73,Orders_Raw!A:A,Orders_Raw!B:B),Customers_Raw!A:A,Customers_Raw!E:E) -> Corporate | N73: =IF(COUNTIF($A$2:A73,A73)=1,1,0) -> 1
A74: O50370 | B74: P1020 | C74: 4 | D74: 31376.79 | E74: =_xlfn.XLOOKUP(Order_Items_Raw!B907,Products_Raw!A:A,Products_Raw!D:D) -> 11764.29 | F74: =D74-(C74*E74) -> -15680.37 | G74: =PROPER(TRIM(CLEAN(_xlfn.XLOOKUP(Order_Items_Raw!A907,Orders_Raw!A:A,Orders_Raw!E:E)))) -> Marketplace | H74: =_xlfn.XLOOKUP(B74,Products_Raw!A:A,Products_Raw!C:C) -> Home & Kitchen | I74: =_xlfn.XLOOKUP(_xlfn.XLOOKUP(A74,Orders_Raw!A:A,Orders_Raw!B:B),Customers_Raw!A:A,Customers_Raw!E:E) -> Consumer | J74: =_xlfn.XLOOKUP(Order_Items_Raw!A907,Orders_Raw!A:A,Orders_Raw!C:C) -> 46001 | K74: Dec | L74: =_xlfn.XLOOKUP(A74,Orders_Raw!A:A,Orders_Raw!D:D) -> Delivered | M74: =_xlfn.XLOOKUP(_xlfn.XLOOKUP(A74,Orders_Raw!A:A,Orders_Raw!B:B),Customers_Raw!A:A,Customers_Raw!E:E) -> Consumer | N74: =IF(COUNTIF($A$2:A74,A74)=1,1,0) -> 1
A75: O50533 | B75: P1020 | C75: 3 | D75: 26268.78 | E75: =_xlfn.XLOOKUP(Order_Items_Raw!B909,Products_Raw!A:A,Products_Raw!D:D) -> 5812.86 | F75: =D75-(C75*E75) -> 8830.2 | G75: =PROPER(TRIM(CLEAN(_xlfn.XLOOKUP(Order_Items_Raw!A909,Orders_Raw!A:A,Orders_Raw!E:E)))) -> Mobile App | H75: =_xlfn.XLOOKUP(B75,Products_Raw!A:A,Products_Raw!C:C) -> Home & Kitchen | I75: =_xlfn.XLOOKUP(_xlfn.XLOOKUP(A75,Orders_Raw!A:A,Orders_Raw!B:B),Customers_Raw!A:A,Customers_Raw!E:E) -> Small Business | J75: =_xlfn.XLOOKUP(Order_Items_Raw!A909,Orders_Raw!A:A,Orders_Raw!C:C) -> 46001 | K75: Dec | L75: =_xlfn.XLOOKUP(A75,Orders_Raw!A:A,Orders_Raw!D:D) -> Delivered | M75: =_xlfn.XLOOKUP(_xlfn.XLOOKUP(A75,Orders_Raw!A:A,Orders_Raw!B:B),Customers_Raw!A:A,Customers_Raw!E:E) -> Small Business | N75: =IF(COUNTIF($A$2:A75,A75)=1,1,0) -> 1
A76: O50181 | B76: P1021 | C76: 2 | D76: 5762.35 | E76: =_xlfn.XLOOKUP(Order_Items_Raw!B958,Products_Raw!A:A,Products_Raw!D:D) -> 4703.24 | F76: =D76-(C76*E76) -> -3644.13 | G76: =PROPER(TRIM(CLEAN(_xlfn.XLOOKUP(Order_Items_Raw!A958,Orders_Raw!A:A,Orders_Raw!E:E)))) -> Website | H76: =_xlfn.XLOOKUP(B76,Products_Raw!A:A,Products_Raw!C:C) -> Home & Kitchen | I76: =_xlfn.XLOOKUP(_xlfn.XLOOKUP(A76,Orders_Raw!A:A,Orders_Raw!B:B),Customers_Raw!A:A,Customers_Raw!E:E) -> Corporate | J76: =_xlfn.XLOOKUP(Order_Items_Raw!A958,Orders_Raw!A:A,Orders_Raw!C:C) -> 45710 | K76: Feb | L76: =_xlfn.XLOOKUP(A76,Orders_Raw!A:A,Orders_Raw!D:D) -> Delivered | M76: =_xlfn.XLOOKUP(_xlfn.XLOOKUP(A76,Orders_Raw!A:A,Orders_Raw!B:B),Customers_Raw!A:A,Customers_Raw!E:E) -> Corporate | N76: =IF(COUNTIF($A$2:A76,A76)=1,1,0) -> 1
A77: O50346 | B77: P1021 | C77: 2 | D77: 5437.84 | E77: =_xlfn.XLOOKUP(Order_Items_Raw!B965,Products_Raw!A:A,Products_Raw!D:D) -> 7014.31 | F77: =D77-(C77*E77) -> -8590.78 | G77: =PROPER(TRIM(CLEAN(_xlfn.XLOOKUP(Order_Items_Raw!A965,Orders_Raw!A:A,Orders_Raw!E:E)))) -> Website | H77: =_xlfn.XLOOKUP(B77,Products_Raw!A:A,Products_Raw!C:C) -> Home & Kitchen | I77: =_xlfn.XLOOKUP(_xlfn.XLOOKUP(A77,Orders_Raw!A:A,Orders_Raw!B:B),Customers_Raw!A:A,Customers_Raw!E:E) -> Consumer | J77: =_xlfn.XLOOKUP(Order_Items_Raw!A965,Orders_Raw!A:A,Orders_Raw!C:C) -> 45714 | K77: Feb | L77: =_xlfn.XLOOKUP(A77,Orders_Raw!A:A,Orders_Raw!D:D) -> Delivered | M77: =_xlfn.XLOOKUP(_xlfn.XLOOKUP(A77,Orders_Raw!A:A,Orders_Raw!B:B),Customers_Raw!A:A,Customers_Raw!E:E) -> Consumer | N77: =IF(COUNTIF($A$2:A77,A77)=1,1,0) -> 1
A78: O50417 | B78: P1021 | C78: 4 | D78: 13026.69 | E78: =_xlfn.XLOOKUP(Order_Items_Raw!B969,Products_Raw!A:A,Products_Raw!D:D) -> 9148.31 | F78: =D78-(C78*E78) -> -23566.55 | G78: =PROPER(TRIM(CLEAN(_xlfn.XLOOKUP(Order_Items_Raw!A969,Orders_Raw!A:A,Orders_Raw!E:E)))) -> Website | H78: =_xlfn.XLOOKUP(B78,Products_Raw!A:A,Products_Raw!C:C) -> Home & Kitchen | I78: =_xlfn.XLOOKUP(_xlfn.XLOOKUP(A78,Orders_Raw!A:A,Orders_Raw!B:B),Customers_Raw!A:A,Customers_Raw!E:E) -> Small Business | J78: =_xlfn.XLOOKUP(Order_Items_Raw!A969,Orders_Raw!A:A,Orders_Raw!C:C) -> 45702 | K78: Feb | L78: =_xlfn.XLOOKUP(A78,Orders_Raw!A:A,Orders_Raw!D:D) -> Delivered | M78: =_xlfn.XLOOKUP(_xlfn.XLOOKUP(A78,Orders_Raw!A:A,Orders_Raw!B:B),Customers_Raw!A:A,Customers_Raw!E:E) -> Small Business | N78: =IF(COUNTIF($A$2:A78,A78)=1,1,0) -> 1
A79: O50542 | B79: P1021 | C79: 4 | D79: 10823.24 | E79: =_xlfn.XLOOKUP(Order_Items_Raw!B974,Products_Raw!A:A,Products_Raw!D:D) -> 1321.65 | F79: =D79-(C79*E79) -> 5536.64 | G79: =PROPER(TRIM(CLEAN(_xlfn.XLOOKUP(Order_Items_Raw!A974,Orders_Raw!A:A,Orders_Raw!E:E)))) -> Mobile App | H79: =_xlfn.XLOOKUP(B79,Products_Raw!A:A,Products_Raw!C:C) -> Home & Kitchen | I79: =_xlfn.XLOOKUP(_xlfn.XLOOKUP(A79,Orders_Raw!A:A,Orders_Raw!B:B),Customers_Raw!A:A,Customers_Raw!E:E) -> Consumer | J79: =_xlfn.XLOOKUP(Order_Items_Raw!A974,Orders_Raw!A:A,Orders_Raw!C:C) -> 45700 | K79: Feb | L79: =_xlfn.XLOOKUP(A79,Orders_Raw!A:A,Orders_Raw!D:D) -> Delivered | M79: =_xlfn.XLOOKUP(_xlfn.XLOOKUP(A79,Orders_Raw!A:A,Orders_Raw!B:B),Customers_Raw!A:A,Customers_Raw!E:E) -> Consumer | N79: =IF(COUNTIF($A$2:A79,A79)=1,1,0) -> 1
A80: O51330 | B80: P1021 | C80: 2 | D80: 6010 | E80: =_xlfn.XLOOKUP(Order_Items_Raw!B992,Products_Raw!A:A,Products_Raw!D:D) -> 6213.42 | F80: =D80-(C80*E80) -> -6416.84 | G80: =PROPER(TRIM(CLEAN(_xlfn.XLOOKUP(Order_Items_Raw!A992,Orders_Raw!A:A,Orders_Raw!E:E)))) -> Marketplace | H80: =_xlfn.XLOOKUP(B80,Products_Raw!A:A,Products_Raw!C:C) -> Home & Kitchen | I80: =_xlfn.XLOOKUP(_xlfn.XLOOKUP(A80,Orders_Raw!A:A,Orders_Raw!B:B),Customers_Raw!A:A,Customers_Raw!E:E) -> Consumer | J80: =_xlfn.XLOOKUP(Order_Items_Raw!A992,Orders_Raw!A:A,Orders_Raw!C:C) -> 45704 | K80: Feb | L80: =_xlfn.XLOOKUP(A80,Orders_Raw!A:A,Orders_Raw!D:D) -> Cancelled | M80: =_xlfn.XLOOKUP(_xlfn.XLOOKUP(A80,Orders_Raw!A:A,Orders_Raw!B:B),Customers_Raw!A:A,Customers_Raw!E:E) -> Consumer | N80: =IF(COUNTIF($A$2:A80,A80)=1,1,0) -> 1
A81: O51713 | B81: P1021 | C81: 3 | D81: 8110.3 | E81: =_xlfn.XLOOKUP(Order_Items_Raw!B998,Products_Raw!A:A,Products_Raw!D:D) -> 2112.7 | F81: =D81-(C81*E81) -> 1772.2 | G81: =PROPER(TRIM(CLEAN(_xlfn.XLOOKUP(Order_Items_Raw!A998,Orders_Raw!A:A,Orders_Raw!E:E)))) -> Marketplace | H81: =_xlfn.XLOOKUP(B81,Products_Raw!A:A,Products_Raw!C:C) -> Home & Kitchen | I81: =_xlfn.XLOOKUP(_xlfn.XLOOKUP(A81,Orders_Raw!A:A,Orders_Raw!B:B),Customers_Raw!A:A,Customers_Raw!E:E) -> Consumer | J81: =_xlfn.XLOOKUP(Order_Items_Raw!A998,Orders_Raw!A:A,Orders_Raw!C:C) -> 45697 | K81: Feb | L81: =_xlfn.XLOOKUP(A81,Orders_Raw!A:A,Orders_Raw!D:D) -> Delivered | M81: =_xlfn.XLOOKUP(_xlfn.XLOOKUP(A81,Orders_Raw!A:A,Orders_Raw!B:B),Customers_Raw!A:A,Customers_Raw!E:E) -> Consumer | N81: =IF(COUNTIF($A$2:A81,A81)=1,1,0) -> 1
A82: O52039 | B82: P1021 | C82: 4 | D82: 13923.39 | E82: =_xlfn.XLOOKUP(Order_Items_Raw!B1001,Products_Raw!A:A,Products_Raw!D:D) -> 2112.7 | F82: =D82-(C82*E82) -> 5472.59 | G82: =PROPER(TRIM(CLEAN(_xlfn.XLOOKUP(Order_Items_Raw!A1001,Orders_Raw!A:A,Orders_Raw!E:E)))) -> Website | H82: =_xlfn.XLOOKUP(B82,Products_Raw!A:A,Products_Raw!C:C) -> Home & Kitchen | I82: =_xlfn.XLOOKUP(_xlfn.XLOOKUP(A82,Orders_Raw!A:A,Orders_Raw!B:B),Customers_Raw!A:A,Customers_Raw!E:E) -> Consumer | J82: =_xlfn.XLOOKUP(Order_Items_Raw!A1001,Orders_Raw!A:A,Orders_Raw!C:C) -> 45712 | K82: Feb | L82: =_xlfn.XLOOKUP(A82,Orders_Raw!A:A,Orders_Raw!D:D) -> Delivered | M82: =_xlfn.XLOOKUP(_xlfn.XLOOKUP(A82,Orders_Raw!A:A,Orders_Raw!B:B),Customers_Raw!A:A,Customers_Raw!E:E) -> Consumer | N82: =IF(COUNTIF($A$2:A82,A82)=1,1,0) -> 1
A83: O52492 | B83: P1021 | C83: 4 | D83: 12406.67 | E83: =_xlfn.XLOOKUP(Order_Items_Raw!B1009,Products_Raw!A:A,Products_Raw!D:D) -> 9178.6 | F83: =D83-(C83*E83) -> -24307.73 | G83: =PROPER(TRIM(CLEAN(_xlfn.XLOOKUP(Order_Items_Raw!A1009,Orders_Raw!A:A,Orders_Raw!E:E)))) -> Mobile App | H83: =_xlfn.XLOOKUP(B83,Products_Raw!A:A,Products_Raw!C:C) -> Home & Kitchen | I83: =_xlfn.XLOOKUP(_xlfn.XLOOKUP(A83,Orders_Raw!A:A,Orders_Raw!B:B),Customers_Raw!A:A,Customers_Raw!E:E) -> Corporate | J83: =_xlfn.XLOOKUP(Order_Items_Raw!A1009,Orders_Raw!A:A,Orders_Raw!C:C) -> 45695 | K83: Feb | L83: =_xlfn.XLOOKUP(A83,Orders_Raw!A:A,Orders_Raw!D:D) -> Delivered | M83: =_xlfn.XLOOKUP(_xlfn.XLOOKUP(A83,Orders_Raw!A:A,Orders_Raw!B:B),Customers_Raw!A:A,Customers_Raw!E:E) -> Corporate | N83: =IF(COUNTIF($A$2:A83,A83)=1,1,0) -> 1
A84: O50419 | B84: P1022 | C84: 4 | D84: 46379.96 | E84: =_xlfn.XLOOKUP(Order_Items_Raw!B1023,Products_Raw!A:A,Products_Raw!D:D) -> 6279.29 | F84: =D84-(C84*E84) -> 21262.8 | G84: =PROPER(TRIM(CLEAN(_xlfn.XLOOKUP(Order_Items_Raw!A1023,Orders_Raw!A:A,Orders_Raw!E:E)))) -> Website | H84: =_xlfn.XLOOKUP(B84,Products_Raw!A:A,Products_Raw!C:C) -> Beauty | I84: =_xlfn.XLOOKUP(_xlfn.XLOOKUP(A84,Orders_Raw!A:A,Orders_Raw!B:B),Customers_Raw!A:A,Customers_Raw!E:E) -> Small Business | J84: =_xlfn.XLOOKUP(Order_Items_Raw!A1023,Orders_Raw!A:A,Orders_Raw!C:C) -> 45691 | K84: Feb | L84: =_xlfn.XLOOKUP(A84,Orders_Raw!A:A,Orders_Raw!D:D) -> Delivered | M84: =_xlfn.XLOOKUP(_xlfn.XLOOKUP(A84,Orders_Raw!A:A,Orders_Raw!B:B),Customers_Raw!A:A,Customers_Raw!E:E) -> Small Business | N84: =IF(COUNTIF($A$2:A84,A84)=1,1,0) -> 1
A85: O50633 | B85: P1022 | C85: 4 | D85: 43465.26 | E85: =_xlfn.XLOOKUP(Order_Items_Raw!B1029,Products_Raw!A:A,Products_Raw!D:D) -> 4640.09 | F85: =D85-(C85*E85) -> 24904.9 | G85: =PROPER(TRIM(CLEAN(_xlfn.XLOOKUP(Order_Items_Raw!A1029,Orders_Raw!A:A,Orders_Raw!E:E)))) -> Website | H85: =_xlfn.XLOOKUP(B85,Products_Raw!A:A,Products_Raw!C:C) -> Beauty | I85: =_xlfn.XLOOKUP(_xlfn.XLOOKUP(A85,Orders_Raw!A:A,Orders_Raw!B:B),Customers_Raw!A:A,Customers_Raw!E:E) -> Corporate | J85: =_xlfn.XLOOKUP(Order_Items_Raw!A1029,Orders_Raw!A:A,Orders_Raw!C:C) -> 45692 | K85: Feb | L85: =_xlfn.XLOOKUP(A85,Orders_Raw!A:A,Orders_Raw!D:D) -> Delivered | M85: =_xlfn.XLOOKUP(_xlfn.XLOOKUP(A85,Orders_Raw!A:A,Orders_Raw!B:B),Customers_Raw!A:A,Customers_Raw!E:E) -> Corporate | N85: =IF(COUNTIF($A$2:A85,A85)=1,1,0) -> 0
A86: O51019 | B86: P1022 | C86: 2 | D86: 19206.47 | E86: =_xlfn.XLOOKUP(Order_Items_Raw!B1037,Products_Raw!A:A,Products_Raw!D:D) -> 9531.89 | F86: =D86-(C86*E86) -> 142.69 | G86: =PROPER(TRIM(CLEAN(_xlfn.XLOOKUP(Order_Items_Raw!A1037,Orders_Raw!A:A,Orders_Raw!E:E)))) -> Website | H86: =_xlfn.XLOOKUP(B86,Products_Raw!A:A,Products_Raw!C:C) -> Beauty | I86: =_xlfn.XLOOKUP(_xlfn.XLOOKUP(A86,Orders_Raw!A:A,Orders_Raw!B:B),Customers_Raw!A:A,Customers_Raw!E:E) -> Consumer | J86: =_xlfn.XLOOKUP(Order_Items_Raw!A1037,Orders_Raw!A:A,Orders_Raw!C:C) -> 45706 | K86: Feb | L86: =_xlfn.XLOOKUP(A86,Orders_Raw!A:A,Orders_Raw!D:D) -> Delivered | M86: =_xlfn.XLOOKUP(_xlfn.XLOOKUP(A86,Orders_Raw!A:A,Orders_Raw!B:B),Customers_Raw!A:A,Customers_Raw!E:E) -> Consumer | N86: =IF(COUNTIF($A$2:A86,A86)=1,1,0) -> 1
A87: O51926 | B87: P1022 | C87: 4 | D87: 39306.93 | E87: =_xlfn.XLOOKUP(Order_Items_Raw!B1051,Products_Raw!A:A,Products_Raw!D:D) -> 6443.36 | F87: =D87-(C87*E87) -> 13533.49 | G87: =PROPER(TRIM(CLEAN(_xlfn.XLOOKUP(Order_Items_Raw!A1051,Orders_Raw!A:A,Orders_Raw!E:E)))) -> Mobile App | H87: =_xlfn.XLOOKUP(B87,Products_Raw!A:A,Products_Raw!C:C) -> Beauty | I87: =_xlfn.XLOOKUP(_xlfn.XLOOKUP(A87,Orders_Raw!A:A,Orders_Raw!B:B),Customers_Raw!A:A,Customers_Raw!E:E) -> Corporate | J87: =_xlfn.XLOOKUP(Order_Items_Raw!A1051,Orders_Raw!A:A,Orders_Raw!C:C) -> 45700 | K87: Feb | L87: =_xlfn.XLOOKUP(A87,Orders_Raw!A:A,Orders_Raw!D:D) -> Shipped | M87: =_xlfn.XLOOKUP(_xlfn.XLOOKUP(A87,Orders_Raw!A:A,Orders_Raw!B:B),Customers_Raw!A:A,Customers_Raw!E:E) -> Corporate | N87: =IF(COUNTIF($A$2:A87,A87)=1,1,0) -> 1
A88: O50095 | B88: P1023 | C88: 4 | D88: 3190.37 | E88: =_xlfn.XLOOKUP(Order_Items_Raw!B1062,Products_Raw!A:A,Products_Raw!D:D) -> 2133.21 | F88: =D88-(C88*E88) -> -5342.47 | G88: =PROPER(TRIM(CLEAN(_xlfn.XLOOKUP(Order_Items_Raw!A1062,Orders_Raw!A:A,Orders_Raw!E:E)))) -> Mobile App | H88: =_xlfn.XLOOKUP(B88,Products_Raw!A:A,Products_Raw!C:C) -> Fashion | I88: =_xlfn.XLOOKUP(_xlfn.XLOOKUP(A88,Orders_Raw!A:A,Orders_Raw!B:B),Customers_Raw!A:A,Customers_Raw!E:E) -> Corporate | J88: =_xlfn.XLOOKUP(Order_Items_Raw!A1062,Orders_Raw!A:A,Orders_Raw!C:C) -> 45708 | K88: Feb | L88: =_xlfn.XLOOKUP(A88,Orders_Raw!A:A,Orders_Raw!D:D) -> Cancelled | M88: =_xlfn.XLOOKUP(_xlfn.XLOOKUP(A88,Orders_Raw!A:A,Orders_Raw!B:B),Customers_Raw!A:A,Customers_Raw!E:E) -> Corporate | N88: =IF(COUNTIF($A$2:A88,A88)=1,1,0) -> 0
A89: O50438 | B89: P1023 | C89: 3 | D89: 3286.82 | E89: =_xlfn.XLOOKUP(Order_Items_Raw!B1069,Products_Raw!A:A,Products_Raw!D:D) -> 11668.5 | F89: =D89-(C89*E89) -> -31718.68 | G89: =PROPER(TRIM(CLEAN(_xlfn.XLOOKUP(Order_Items_Raw!A1069,Orders_Raw!A:A,Orders_Raw!E:E)))) -> Marketplace | H89: =_xlfn.XLOOKUP(B89,Products_Raw!A:A,Products_Raw!C:C) -> Fashion | I89: =_xlfn.XLOOKUP(_xlfn.XLOOKUP(A89,Orders_Raw!A:A,Orders_Raw!B:B),Customers_Raw!A:A,Customers_Raw!E:E) -> Corporate | J89: =_xlfn.XLOOKUP(Order_Items_Raw!A1069,Orders_Raw!A:A,Orders_Raw!C:C) -> 45705 | K89: Feb | L89: =_xlfn.XLOOKUP(A89,Orders_Raw!A:A,Orders_Raw!D:D) -> Delivered | M89: =_xlfn.XLOOKUP(_xlfn.XLOOKUP(A89,Orders_Raw!A:A,Orders_Raw!B:B),Customers_Raw!A:A,Customers_Raw!E:E) -> Corporate | N89: =IF(COUNTIF($A$2:A89,A89)=1,1,0) -> 1
A90: O50533 | B90: P1023 | C90: 2 | D90: 1649.97 | E90: =_xlfn.XLOOKUP(Order_Items_Raw!B1071,Products_Raw!A:A,Products_Raw!D:D) -> 2857.57 | F90: =D90-(C90*E90) -> -4065.17 | G90: =PROPER(TRIM(CLEAN(_xlfn.XLOOKUP(Order_Items_Raw!A1071,Orders_Raw!A:A,Orders_Raw!E:E)))) -> Mobile App | H90: =_xlfn.XLOOKUP(B90,Products_Raw!A:A,Products_Raw!C:C) -> Fashion | I90: =_xlfn.XLOOKUP(_xlfn.XLOOKUP(A90,Orders_Raw!A:A,Orders_Raw!B:B),Customers_Raw!A:A,Customers_Raw!E:E) -> Small Business | J90: =_xlfn.XLOOKUP(Order_Items_Raw!A1071,Orders_Raw!A:A,Orders_Raw!C:C) -> 45715 | K90: Feb | L90: =_xlfn.XLOOKUP(A90,Orders_Raw!A:A,Orders_Raw!D:D) -> Delivered | M90: =_xlfn.XLOOKUP(_xlfn.XLOOKUP(A90,Orders_Raw!A:A,Orders_Raw!B:B),Customers_Raw!A:A,Customers_Raw!E:E) -> Small Business | N90: =IF(COUNTIF($A$2:A90,A90)=1,1,0) -> 0
A91: O52349 | B91: P1024 | C91: 3 | D91: 34265.83 | E91: =_xlfn.XLOOKUP(Order_Items_Raw!B1155,Products_Raw!A:A,Products_Raw!D:D) -> 6457.25 | F91: =D91-(C91*E91) -> 14894.08 | G91: =PROPER(TRIM(CLEAN(_xlfn.XLOOKUP(Order_Items_Raw!A1155,Orders_Raw!A:A,Orders_Raw!E:E)))) -> Website | H91: =_xlfn.XLOOKUP(B91,Products_Raw!A:A,Products_Raw!C:C) -> Electronics | I91: =_xlfn.XLOOKUP(_xlfn.XLOOKUP(A91,Orders_Raw!A:A,Orders_Raw!B:B),Customers_Raw!A:A,Customers_Raw!E:E) -> Corporate | J91: =_xlfn.XLOOKUP(Order_Items_Raw!A1155,Orders_Raw!A:A,Orders_Raw!C:C) -> 45712 | K91: Feb | L91: =_xlfn.XLOOKUP(A91,Orders_Raw!A:A,Orders_Raw!D:D) -> Shipped | M91: =_xlfn.XLOOKUP(_xlfn.XLOOKUP(A91,Orders_Raw!A:A,Orders_Raw!B:B),Customers_Raw!A:A,Customers_Raw!E:E) -> Corporate | N91: =IF(COUNTIF($A$2:A91,A91)=1,1,0) -> 1
A92: O50129 | B92: P1025 | C92: 1 | D92: 15769.46 | E92: =_xlfn.XLOOKUP(Order_Items_Raw!B1161,Products_Raw!A:A,Products_Raw!D:D) -> 2144.79 | F92: =D92-(C92*E92) -> 13624.67 | G92: =PROPER(TRIM(CLEAN(_xlfn.XLOOKUP(Order_Items_Raw!A1161,Orders_Raw!A:A,Orders_Raw!E:E)))) -> Marketplace | H92: =_xlfn.XLOOKUP(B92,Products_Raw!A:A,Products_Raw!C:C) -> Beauty | I92: =_xlfn.XLOOKUP(_xlfn.XLOOKUP(A92,Orders_Raw!A:A,Orders_Raw!B:B),Customers_Raw!A:A,Customers_Raw!E:E) -> Corporate | J92: =_xlfn.XLOOKUP(Order_Items_Raw!A1161,Orders_Raw!A:A,Orders_Raw!C:C) -> 45700 | K92: Feb | L92: =_xlfn.XLOOKUP(A92,Orders_Raw!A:A,Orders_Raw!D:D) -> Delivered | M92: =_xlfn.XLOOKUP(_xlfn.XLOOKUP(A92,Orders_Raw!A:A,Orders_Raw!B:B),Customers_Raw!A:A,Customers_Raw!E:E) -> Corporate | N92: =IF(COUNTIF($A$2:A92,A92)=1,1,0) -> 1
A93: O50508 | B93: P1025 | C93: 1 | D93: 16747.29 | E93: =_xlfn.XLOOKUP(Order_Items_Raw!B1167,Products_Raw!A:A,Products_Raw!D:D) -> 10086.81 | F93: =D93-(C93*E93) -> 6660.48 | G93: =PROPER(TRIM(CLEAN(_xlfn.XLOOKUP(Order_Items_Raw!A1167,Orders_Raw!A:A,Orders_Raw!E:E)))) -> Website | H93: =_xlfn.XLOOKUP(B93,Products_Raw!A:A,Products_Raw!C:C) -> Beauty | I93: =_xlfn.XLOOKUP(_xlfn.XLOOKUP(A93,Orders_Raw!A:A,Orders_Raw!B:B),Customers_Raw!A:A,Customers_Raw!E:E) -> Consumer | J93: =_xlfn.XLOOKUP(Order_Items_Raw!A1167,Orders_Raw!A:A,Orders_Raw!C:C) -> 45714 | K93: Feb | L93: =_xlfn.XLOOKUP(A93,Orders_Raw!A:A,Orders_Raw!D:D) -> Delivered | M93: =_xlfn.XLOOKUP(_xlfn.XLOOKUP(A93,Orders_Raw!A:A,Orders_Raw!B:B),Customers_Raw!A:A,Customers_Raw!E:E) -> Consumer | N93: =IF(COUNTIF($A$2:A93,A93)=1,1,0) -> 1
A94: O51330 | B94: P1025 | C94: 3 | D94: 49072.05 | E94: =_xlfn.XLOOKUP(Order_Items_Raw!B1175,Products_Raw!A:A,Products_Raw!D:D) -> 4370.8 | F94: =D94-(C94*E94) -> 35959.65 | G94: =PROPER(TRIM(CLEAN(_xlfn.XLOOKUP(Order_Items_Raw!A1175,Orders_Raw!A:A,Orders_Raw!E:E)))) -> Marketplace | H94: =_xlfn.XLOOKUP(B94,Products_Raw!A:A,Products_Raw!C:C) -> Beauty | I94: =_xlfn.XLOOKUP(_xlfn.XLOOKUP(A94,Orders_Raw!A:A,Orders_Raw!B:B),Customers_Raw!A:A,Customers_Raw!E:E) -> Consumer | J94: =_xlfn.XLOOKUP(Order_Items_Raw!A1175,Orders_Raw!A:A,Orders_Raw!C:C) -> 45704 | K94: Feb | L94: =_xlfn.XLOOKUP(A94,Orders_Raw!A:A,Orders_Raw!D:D) -> Cancelled | M94: =_xlfn.XLOOKUP(_xlfn.XLOOKUP(A94,Orders_Raw!A:A,Orders_Raw!B:B),Customers_Raw!A:A,Customers_Raw!E:E) -> Consumer | N94: =IF(COUNTIF($A$2:A94,A94)=1,1,0) -> 0
A95: O51542 | B95: P1025 | C95: 2 | D95: 28549.49 | E95: =_xlfn.XLOOKUP(Order_Items_Raw!B1181,Products_Raw!A:A,Products_Raw!D:D) -> 8551.81 | F95: =D95-(C95*E95) -> 11445.87 | G95: =PROPER(TRIM(CLEAN(_xlfn.XLOOKUP(Order_Items_Raw!A1181,Orders_Raw!A:A,Orders_Raw!E:E)))) -> Website | H95: =_xlfn.XLOOKUP(B95,Products_Raw!A:A,Products_Raw!C:C) -> Beauty | I95: =_xlfn.XLOOKUP(_xlfn.XLOOKUP(A95,Orders_Raw!A:A,Orders_Raw!B:B),Customers_Raw!A:A,Customers_Raw!E:E) -> Consumer | J95: =_xlfn.XLOOKUP(Order_Items_Raw!A1181,Orders_Raw!A:A,Orders_Raw!C:C) -> 45699 | K95: Feb | L95: =_xlfn.XLOOKUP(A95,Orders_Raw!A:A,Orders_Raw!D:D) -> Delivered | M95: =_xlfn.XLOOKUP(_xlfn.XLOOKUP(A95,Orders_Raw!A:A,Orders_Raw!B:B),Customers_Raw!A:A,Customers_Raw!E:E) -> Consumer | N95: =IF(COUNTIF($A$2:A95,A95)=1,1,0) -> 1
A96: O51649 | B96: P1025 | C96: 1 | D96: 15288.21 | E96: =_xlfn.XLOOKUP(Order_Items_Raw!B1182,Products_Raw!A:A,Products_Raw!D:D) -> 8551.81 | F96: =D96-(C96*E96) -> 6736.4 | G96: =PROPER(TRIM(CLEAN(_xlfn.XLOOKUP(Order_Items_Raw!A1182,Orders_Raw!A:A,Orders_Raw!E:E)))) -> Mobile App | H96: =_xlfn.XLOOKUP(B96,Products_Raw!A:A,Products_Raw!C:C) -> Beauty | I96: =_xlfn.XLOOKUP(_xlfn.XLOOKUP(A96,Orders_Raw!A:A,Orders_Raw!B:B),Customers_Raw!A:A,Customers_Raw!E:E) -> Consumer | J96: =_xlfn.XLOOKUP(Order_Items_Raw!A1182,Orders_Raw!A:A,Orders_Raw!C:C) -> 45706 | K96: Feb | L96: =_xlfn.XLOOKUP(A96,Orders_Raw!A:A,Orders_Raw!D:D) -> Processing | M96: =_xlfn.XLOOKUP(_xlfn.XLOOKUP(A96,Orders_Raw!A:A,Orders_Raw!B:B),Customers_Raw!A:A,Customers_Raw!E:E) -> Consumer | N96: =IF(COUNTIF($A$2:A96,A96)=1,1,0) -> 1
A97: O52308 | B97: P1025 | C97: 4 | D97: 53347.33 | E97: =_xlfn.XLOOKUP(Order_Items_Raw!B1199,Products_Raw!A:A,Products_Raw!D:D) -> 2935.19 | F97: =D97-(C97*E97) -> 41606.57 | G97: =PROPER(TRIM(CLEAN(_xlfn.XLOOKUP(Order_Items_Raw!A1199,Orders_Raw!A:A,Orders_Raw!E:E)))) -> Mobile App | H97: =_xlfn.XLOOKUP(B97,Products_Raw!A:A,Products_Raw!C:C) -> Beauty | I97: =_xlfn.XLOOKUP(_xlfn.XLOOKUP(A97,Orders_Raw!A:A,Orders_Raw!B:B),Customers_Raw!A:A,Customers_Raw!E:E) -> Corporate | J97: =_xlfn.XLOOKUP(Order_Items_Raw!A1199,Orders_Raw!A:A,Orders_Raw!C:C) -> 45716 | K97: Feb | L97: =_xlfn.XLOOKUP(A97,Orders_Raw!A:A,Orders_Raw!D:D) -> Delivered | M97: =_xlfn.XLOOKUP(_xlfn.XLOOKUP(A97,Orders_Raw!A:A,Orders_Raw!B:B),Customers_Raw!A:A,Customers_Raw!E:E) -> Corporate | N97: =IF(COUNTIF($A$2:A97,A97)=1,1,0) -> 1
A98: O50423 | B98: P1026 | C98: 3 | D98: 18136.14 | E98: =_xlfn.XLOOKUP(Order_Items_Raw!B1208,Products_Raw!A:A,Products_Raw!D:D) -> 10244.32 | F98: =D98-(C98*E98) -> -12596.82 | G98: =PROPER(TRIM(CLEAN(_xlfn.XLOOKUP(Order_Items_Raw!A1208,Orders_Raw!A:A,Orders_Raw!E:E)))) -> Marketplace | H98: =_xlfn.XLOOKUP(B98,Products_Raw!A:A,Products_Raw!C:C) -> Home & Kitchen | I98: =_xlfn.XLOOKUP(_xlfn.XLOOKUP(A98,Orders_Raw!A:A,Orders_Raw!B:B),Customers_Raw!A:A,Customers_Raw!E:E) -> Consumer | J98: =_xlfn.XLOOKUP(Order_Items_Raw!A1208,Orders_Raw!A:A,Orders_Raw!C:C) -> 45673 | K98: Jan | L98: =_xlfn.XLOOKUP(A98,Orders_Raw!A:A,Orders_Raw!D:D) -> Delivered | M98: =_xlfn.XLOOKUP(_xlfn.XLOOKUP(A98,Orders_Raw!A:A,Orders_Raw!B:B),Customers_Raw!A:A,Customers_Raw!E:E) -> Consumer | N98: =IF(COUNTIF($A$2:A98,A98)=1,1,0) -> 1
A99: O51213 | B99: P1026 | C99: 3 | D99: 16689.84 | E99: =_xlfn.XLOOKUP(Order_Items_Raw!B1227,Products_Raw!A:A,Products_Raw!D:D) -> 10361.65 | F99: =D99-(C99*E99) -> -14395.11 | G99: =PROPER(TRIM(CLEAN(_xlfn.XLOOKUP(Order_Items_Raw!A1227,Orders_Raw!A:A,Orders_Raw!E:E)))) -> Mobile App | H99: =_xlfn.XLOOKUP(B99,Products_Raw!A:A,Products_Raw!C:C) -> Home & Kitchen | I99: =_xlfn.XLOOKUP(_xlfn.XLOOKUP(A99,Orders_Raw!A:A,Orders_Raw!B:B),Customers_Raw!A:A,Customers_Raw!E:E) -> Consumer | J99: =_xlfn.XLOOKUP(Order_Items_Raw!A1227,Orders_Raw!A:A,Orders_Raw!C:C) -> 45659 | K99: Jan | L99: =_xlfn.XLOOKUP(A99,Orders_Raw!A:A,Orders_Raw!D:D) -> Delivered | M99: =_xlfn.XLOOKUP(_xlfn.XLOOKUP(A99,Orders_Raw!A:A,Orders_Raw!B:B),Customers_Raw!A:A,Customers_Raw!E:E) -> Consumer | N99: =IF(COUNTIF($A$2:A99,A99)=1,1,0) -> 1
A100: O51265 | B100: P1026 | C100: 2 | D100: 11537.43 | E100: =_xlfn.XLOOKUP(Order_Items_Raw!B1230,Products_Raw!A:A,Products_Raw!D:D) -> 10361.65 | F100: =D100-(C100*E100) -> -9185.87 | G100: =PROPER(TRIM(CLEAN(_xlfn.XLOOKUP(Order_Items_Raw!A1230,Orders_Raw!A:A,Orders_Raw!E:E)))) -> Website | H100: =_xlfn.XLOOKUP(B100,Products_Raw!A:A,Products_Raw!C:C) -> Home & Kitchen | I100: =_xlfn.XLOOKUP(_xlfn.XLOOKUP(A100,Orders_Raw!A:A,Orders_Raw!B:B),Customers_Raw!A:A,Customers_Raw!E:E) -> Consumer | J100: =_xlfn.XLOOKUP(Order_Items_Raw!A1230,Orders_Raw!A:A,Orders_Raw!C:C) -> 45663 | K100: Jan | L100: =_xlfn.XLOOKUP(A100,Orders_Raw!A:A,Orders_Raw!D:D) -> Processing | M100: =_xlfn.XLOOKUP(_xlfn.XLOOKUP(A100,Orders_Raw!A:A,Orders_Raw!B:B),Customers_Raw!A:A,Customers_Raw!E:E) -> Consumer | N100: =IF(COUNTIF($A$2:A100,A100)=1,1,0) -> 1
...

Sheet Returns_Raw
A1: Return_ID | B1: Order_ID | C1: Return_Reason | D1: Refund_Amount
A2: R70001 | B2: O52259 | C2: Wrong Product | D2: 3586.57
A3: R70002 | B3: O51727 | C3: Customer Changed Mind | D3: 62953.3
A4: R70003 | B4: O52468 | C4: Quality Issue | D4: 10785.04
A5: R70004 | B5: O52004 | C5: Damaged | D5: 6574.48
A6: R70005 | B6: O52418 | C6: Damaged | D6: 37099.29
A7: R70006 | B7: O51194 | C7: Late Delivery | D7: 5729.31
A8: R70007 | B8: O51982 | C8: Customer Changed Mind | D8: 60483.17
A9: R70008 | B9: O52184 | C9: Wrong Product | D9: 4641.09
A10: R70009 | B10: O52096 | C10: Wrong Product | D10: 22113.41
A11: R70010 | B11: O50294 | C11: Customer Changed Mind | D11: 27284.51
A12: R70011 | B12: O52399 | C12: Customer Changed Mind | D12: 20370.32
A13: R70012 | B13: O51315 | C13: Customer Changed Mind | D13: 38797.69
... A175: R70174 | B175: O51307 | C175: Customer Changed Mind | D175: 27918.93

Sheet Products_Raw
A1: Product_ID | B1: Product_Name | C1: Category | D1: Unit_Cost
A2: P1001 | B2: Premium Headphones P1001 | C2: Sports | D2: 4740.6
A3: P1002 | B3: Essential Mixer P1002 | C3: Sports | D3: 10244.32
A4: P1003 | B4: Eco Notebook P1003 | C4: Sports | D4: 4936.19
A5: P1004 | B5: Pro Mouse P1004 | C5: Beauty | D5: 1069.73
A6: P1005 | B6: Premium Notebook P1005 | C6: Sports | D6: 6579.03
A7: P1006 | B7: Eco Monitor P1006 | C7: Electronics | D7: 10361.65
A8: P1007 | B8: Premium Keyboard P1007 | C8: Sports | D8: 7144.88
A9: P1008 | B9: Smart Keyboard P1008 | C9: Home & Kitchen | D9: 2831.41
A10: P1009 | B10: Essential Shoes P1009 | C10: Beauty | D10: 4703.24
A11: P1010 | B11: Classic Mixer P1010 | C11: Home & Kitchen | D11: 5483.96
A12: P1011 | B12: Pro Monitor P1011 | C12: Sports | D12: 7014.31
A13: P1012 | B13: Eco Mixer P1012 | C13: Electronics | D13: 9148.31
... A81: P1080 | B81: Essential Shoes P1080 | C81: Beauty | D81: 2935.19

Sheet Returns pivot
A3: Return_Reason | B3: Sum of Refund_Amount | D3: Count of Refund_Amount
A4: Customer Changed Mind | B4: 1029221.2 | D4: 174
A5: Damaged | B5: 491045.15
A6: Late Delivery | B6: 798832.91 | D6: Return Rate
A7: Quality Issue | B7: 721552.3 | D7: =GETPIVOTDATA("Refund_Amount",$D$3)/Dashboard_Pivots!C46 -> 0.046350559
A8: Wrong Product | B8: 718051.53
A9: Grand Total | B9: 3758703.1

Sheet Dashboard_Pivots
A1: Sales_Channel | B1: Sum of Line_Revenue | D1: Category | E1: Sum of Line_Revenue
A2: Marketplace | B2: 14631195 | D2: Beauty | E2: 8462473.1
A3: Mobile App | B3: 26676534 | D3: Electronics | E3: 13975356
A4: Website | B4: 34202096 | D4: Fashion | E4: 10985690
A5: Grand Total | B5: 75509825 | D5: Home & Kitchen | E5: 13519711
D6: Office Supplies | E6: 12320846
A7: Customer_Segment | B7: Sum of Line_Revenue | D7: Sports | E7: 16245748
A8: Consumer | B8: 45586560 | D8: Grand Total | E8: 75509825 | G8: =GETPIVOTDATA("Line_Revenue",$A$1) -> 75509825
A9: Corporate | B9: 20134522
A10: Small Business | B10: 9788743
A11: Grand Total | B11: 75509825
A13: Category | B13: Sum of Gross_Profit | D13: Order_Month | E13: Sum of Gross_Profit
A14: Beauty | B14: 207271.33 | D14: Jan | E14: 1370472
A15: Electronics | B15: 3380811.5 | D15: Feb | E15: 1058395.8
A16: Fashion | B16: 3560057.3 | D16: Mar | E16: 654117.06
A17: Home & Kitchen | B17: 3674266.8 | D17: Apr | E17: 2713319.2
A18: Office Supplies | B18: 4818784.1 | D18: May | E18: 2361286.4
A19: Sports | B19: 5673035.6 | D19: Jun | E19: 2674015.7
A20: Grand Total | B20: 21314226 | D20: Jul | E20: 2382891.1
D21: Aug | E21: 2368936
D22: Sep | E22: 1584602.8
D23: Oct | E23: 2923265.8
D24: Nov | E24: 1841479.3
A25: Total Revenue | D25: Dec | E25: -618554.58
A26: 75509825 | D26: Grand Total | E26: 21314226
A28: Total Units Sold | G28: =GETPIVOTDATA("Gross_Profit",$A$31) -> 21314226
A29: 9419
A31: Total Gross Profit
A32: 21314226 | C32: Average Order Value
C33: =GETPIVOTDATA("Line_Revenue",$A$25)/GETPIVOTDATA("Order_ID",$C$44) -> 20114.498
C35: Gross Margin
C36: =GETPIVOTDATA("Gross_Profit",$A$31)/GETPIVOTDATA("Line_Revenue",$A$25) -> 0.2822709
C44: Count of Order_ID
C45: 3754
C46: =GETPIVOTDATA("Order_ID",$C$44) -> 3754

Sheet Dashboard
